{
"meta":{"test_sets":[],"test_metrics":[],"learn_metrics":[{"best_value":"Min","name":"RMSE"}],"launch_mode":"Train","parameters":"","iteration_count":1000,"learn_sets":["learn"],"name":"experiment"},
"iterations":[
{"learn":[14.59871775],"iteration":0,"passed_time":0.1398505406,"remaining_time":139.7106901},
{"learn":[14.22518863],"iteration":1,"passed_time":0.1424924753,"remaining_time":71.10374516},
{"learn":[13.8866124],"iteration":2,"passed_time":0.144816262,"remaining_time":48.12727108},
{"learn":[13.52356875],"iteration":3,"passed_time":0.147619276,"remaining_time":36.75719972},
{"learn":[13.18870211],"iteration":4,"passed_time":0.1499882398,"remaining_time":29.84765973},
{"learn":[12.9124226],"iteration":5,"passed_time":0.152803419,"remaining_time":25.31443308},
{"learn":[12.60003351],"iteration":6,"passed_time":0.1541340987,"remaining_time":21.86502286},
{"learn":[12.32990573],"iteration":7,"passed_time":0.1574208488,"remaining_time":19.52018525},
{"learn":[12.0660619],"iteration":8,"passed_time":0.1594319608,"remaining_time":17.55523035},
{"learn":[11.77309809],"iteration":9,"passed_time":0.1606808625,"remaining_time":15.90740539},
{"learn":[11.49227636],"iteration":10,"passed_time":0.1611617469,"remaining_time":14.48990615},
{"learn":[11.26264833],"iteration":11,"passed_time":0.1624160395,"remaining_time":13.37225392},
{"learn":[11.04260393],"iteration":12,"passed_time":0.1643657304,"remaining_time":12.479152},
{"learn":[10.79916926],"iteration":13,"passed_time":0.1662046478,"remaining_time":11.70555591},
{"learn":[10.5541002],"iteration":14,"passed_time":0.168178521,"remaining_time":11.04372288},
{"learn":[10.31918115],"iteration":15,"passed_time":0.1693866916,"remaining_time":10.41728153},
{"learn":[10.10004441],"iteration":16,"passed_time":0.1720854581,"remaining_time":9.950588545},
{"learn":[9.894556723],"iteration":17,"passed_time":0.1735861081,"remaining_time":9.470086562},
{"learn":[9.690174082],"iteration":18,"passed_time":0.1740392979,"remaining_time":8.98592375},
{"learn":[9.506034866],"iteration":19,"passed_time":0.1753597032,"remaining_time":8.592625458},
{"learn":[9.338524633],"iteration":20,"passed_time":0.1767810577,"remaining_time":8.241364548},
{"learn":[9.170203312],"iteration":21,"passed_time":0.1781943396,"remaining_time":7.921548371},
{"learn":[9.010299969],"iteration":22,"passed_time":0.1795333757,"remaining_time":7.626265568},
{"learn":[8.843866678],"iteration":23,"passed_time":0.1807807133,"remaining_time":7.351749006},
{"learn":[8.690548059],"iteration":24,"passed_time":0.1821809303,"remaining_time":7.105056283},
{"learn":[8.555307687],"iteration":25,"passed_time":0.1837931272,"remaining_time":6.885173302},
{"learn":[8.413851302],"iteration":26,"passed_time":0.1850339516,"remaining_time":6.668075368},
{"learn":[8.29256019],"iteration":27,"passed_time":0.1862913311,"remaining_time":6.466970494},
{"learn":[8.162193833],"iteration":28,"passed_time":0.1874794719,"remaining_time":6.277329904},
{"learn":[8.040736294],"iteration":29,"passed_time":0.1887139104,"remaining_time":6.101749771},
{"learn":[7.921220278],"iteration":30,"passed_time":0.1899358774,"remaining_time":5.93702791},
{"learn":[7.809589039],"iteration":31,"passed_time":0.1911512555,"remaining_time":5.782325478},
{"learn":[7.699675801],"iteration":32,"passed_time":0.1922937642,"remaining_time":5.634789998},
{"learn":[7.60645267],"iteration":33,"passed_time":0.1933925281,"remaining_time":5.494623004},
{"learn":[7.498880302],"iteration":34,"passed_time":0.1944723441,"remaining_time":5.361880345},
{"learn":[7.401158744],"iteration":35,"passed_time":0.1955162483,"remaining_time":5.235490648},
{"learn":[7.306431077],"iteration":36,"passed_time":0.1967341349,"remaining_time":5.120404646},
{"learn":[7.223863468],"iteration":37,"passed_time":0.1977128164,"remaining_time":5.005256035},
{"learn":[7.143477682],"iteration":38,"passed_time":0.198783116,"remaining_time":4.898219857},
{"learn":[7.062817131],"iteration":39,"passed_time":0.1998877683,"remaining_time":4.797306439},
{"learn":[6.990793435],"iteration":40,"passed_time":0.2008790493,"remaining_time":4.698609958},
{"learn":[6.931862224],"iteration":41,"passed_time":0.2018122618,"remaining_time":4.603241591},
{"learn":[6.858296558],"iteration":42,"passed_time":0.202765673,"remaining_time":4.512715095},
{"learn":[6.786268161],"iteration":43,"passed_time":0.2035542621,"remaining_time":4.422678967},
{"learn":[6.717118549],"iteration":44,"passed_time":0.2043771031,"remaining_time":4.3373363},
{"learn":[6.652948106],"iteration":45,"passed_time":0.2051234847,"remaining_time":4.254082705},
{"learn":[6.589686076],"iteration":46,"passed_time":0.2058790159,"remaining_time":4.174525577},
{"learn":[6.531283097],"iteration":47,"passed_time":0.2066426525,"remaining_time":4.098412608},
{"learn":[6.471368031],"iteration":48,"passed_time":0.2074015631,"remaining_time":4.025283399},
{"learn":[6.416481395],"iteration":49,"passed_time":0.2082332658,"remaining_time":3.956432049},
{"learn":[6.369870822],"iteration":50,"passed_time":0.2088077682,"remaining_time":3.885462197},
{"learn":[6.325678067],"iteration":51,"passed_time":0.2096824952,"remaining_time":3.822673182},
{"learn":[6.275766122],"iteration":52,"passed_time":0.2107036606,"remaining_time":3.764837106},
{"learn":[6.224773967],"iteration":53,"passed_time":0.2114923148,"remaining_time":3.705032033},
{"learn":[6.182249254],"iteration":54,"passed_time":0.2126931087,"remaining_time":3.654454322},
{"learn":[6.139904173],"iteration":55,"passed_time":0.2135939485,"remaining_time":3.600583703},
{"learn":[6.100525536],"iteration":56,"passed_time":0.2143402833,"remaining_time":3.546015565},
{"learn":[6.062568564],"iteration":57,"passed_time":0.2150294651,"remaining_time":3.492375105},
{"learn":[6.030559288],"iteration":58,"passed_time":0.2158176481,"remaining_time":3.442108591},
{"learn":[5.997931376],"iteration":59,"passed_time":0.2165222053,"remaining_time":3.392181216},
{"learn":[5.964103835],"iteration":60,"passed_time":0.2172852613,"remaining_time":3.344768203},
{"learn":[5.933729724],"iteration":61,"passed_time":0.2179757958,"remaining_time":3.297762846},
{"learn":[5.901932711],"iteration":62,"passed_time":0.2186040083,"remaining_time":3.251300885},
{"learn":[5.873727795],"iteration":63,"passed_time":0.2192369469,"remaining_time":3.206340348},
{"learn":[5.846485734],"iteration":64,"passed_time":0.219870584,"remaining_time":3.162753786},
{"learn":[5.820630862],"iteration":65,"passed_time":0.2204785718,"remaining_time":3.120105849},
{"learn":[5.793646238],"iteration":66,"passed_time":0.2211311921,"remaining_time":3.079334361},
{"learn":[5.765388646],"iteration":67,"passed_time":0.2217211434,"remaining_time":3.038883907},
{"learn":[5.747073912],"iteration":68,"passed_time":0.2222859418,"remaining_time":2.999249446},
{"learn":[5.722315217],"iteration":69,"passed_time":0.2229070599,"remaining_time":2.96147951},
{"learn":[5.699970599],"iteration":70,"passed_time":0.2234347314,"remaining_time":2.923533317},
{"learn":[5.682732647],"iteration":71,"passed_time":0.2239765651,"remaining_time":2.886809062},
{"learn":[5.663525791],"iteration":72,"passed_time":0.2245769353,"remaining_time":2.851819438},
{"learn":[5.642381613],"iteration":73,"passed_time":0.2251822927,"remaining_time":2.817821663},
{"learn":[5.621404779],"iteration":74,"passed_time":0.2256600749,"remaining_time":2.783140924},
{"learn":[5.602460129],"iteration":75,"passed_time":0.2261566916,"remaining_time":2.749589251},
{"learn":[5.587337574],"iteration":76,"passed_time":0.2273530038,"remaining_time":2.725283409},
{"learn":[5.572393026],"iteration":77,"passed_time":0.227953212,"remaining_time":2.694523864},
{"learn":[5.558425806],"iteration":78,"passed_time":0.2284955006,"remaining_time":2.663852609},
{"learn":[5.541518902],"iteration":79,"passed_time":0.2290138319,"remaining_time":2.633659067},
{"learn":[5.526157283],"iteration":80,"passed_time":0.2295251477,"remaining_time":2.604118651},
{"learn":[5.511746977],"iteration":81,"passed_time":0.2300193654,"remaining_time":2.575094847},
{"learn":[5.504975022],"iteration":82,"passed_time":0.2302503394,"remaining_time":2.543850135},
{"learn":[5.493980522],"iteration":83,"passed_time":0.2307337568,"remaining_time":2.516096682},
{"learn":[5.480745463],"iteration":84,"passed_time":0.2312458715,"remaining_time":2.489293793},
{"learn":[5.464052013],"iteration":85,"passed_time":0.2316930063,"remaining_time":2.462411718},
{"learn":[5.449143727],"iteration":86,"passed_time":0.2321547307,"remaining_time":2.436290449},
{"learn":[5.438255432],"iteration":87,"passed_time":0.2326474999,"remaining_time":2.41107409},
{"learn":[5.425927931],"iteration":88,"passed_time":0.2332235649,"remaining_time":2.387265929},
{"learn":[5.412331217],"iteration":89,"passed_time":0.2337092328,"remaining_time":2.363060021},
{"learn":[5.400691499],"iteration":90,"passed_time":0.2341555534,"remaining_time":2.338982396},
{"learn":[5.391618744],"iteration":91,"passed_time":0.2346482805,"remaining_time":2.315876508},
{"learn":[5.380766572],"iteration":92,"passed_time":0.2351278773,"remaining_time":2.293128868},
{"learn":[5.372207183],"iteration":93,"passed_time":0.2356247445,"remaining_time":2.271021474},
{"learn":[5.362918837],"iteration":94,"passed_time":0.236061037,"remaining_time":2.248791984},
{"learn":[5.348292324],"iteration":95,"passed_time":0.2365443143,"remaining_time":2.227458959},
{"learn":[5.339772295],"iteration":96,"passed_time":0.2369748688,"remaining_time":2.206065016},
{"learn":[5.331515983],"iteration":97,"passed_time":0.2374828273,"remaining_time":2.185811329},
{"learn":[5.323861644],"iteration":98,"passed_time":0.2379558429,"remaining_time":2.16563853},
{"learn":[5.313277281],"iteration":99,"passed_time":0.2384426674,"remaining_time":2.145984006},
{"learn":[5.30685627],"iteration":100,"passed_time":0.2389127125,"remaining_time":2.126559688},
{"learn":[5.29652059],"iteration":101,"passed_time":0.2394668592,"remaining_time":2.108247447},
{"learn":[5.288350766],"iteration":102,"passed_time":0.2400551798,"remaining_time":2.090577634},
{"learn":[5.27993346],"iteration":103,"passed_time":0.2406321449,"remaining_time":2.073138479},
{"learn":[5.271789139],"iteration":104,"passed_time":0.2412297108,"remaining_time":2.056196106},
{"learn":[5.262684686],"iteration":105,"passed_time":0.2417477556,"remaining_time":2.038891448},
{"learn":[5.251619772],"iteration":106,"passed_time":0.2423388521,"remaining_time":2.022510233},
{"learn":[5.241012171],"iteration":107,"passed_time":0.2428836486,"remaining_time":2.006039024},
{"learn":[5.232684032],"iteration":108,"passed_time":0.2434176295,"remaining_time":1.989771632},
{"learn":[5.224267141],"iteration":109,"passed_time":0.2439635313,"remaining_time":1.973886753},
{"learn":[5.216324968],"iteration":110,"passed_time":0.2444527778,"remaining_time":1.9578245},
{"learn":[5.211102527],"iteration":111,"passed_time":0.2449709697,"remaining_time":1.942269831},
{"learn":[5.206364257],"iteration":112,"passed_time":0.2454578716,"remaining_time":1.926735682},
{"learn":[5.196937641],"iteration":113,"passed_time":0.2459356974,"remaining_time":1.911394982},
{"learn":[5.190746047],"iteration":114,"passed_time":0.2464288803,"remaining_time":1.896430948},
{"learn":[5.181885213],"iteration":115,"passed_time":0.2469143299,"remaining_time":1.881657479},
{"learn":[5.178293568],"iteration":116,"passed_time":0.2472774757,"remaining_time":1.866205223},
{"learn":[5.170991438],"iteration":117,"passed_time":0.2477832933,"remaining_time":1.852075124},
{"learn":[5.166257212],"iteration":118,"passed_time":0.2482579289,"remaining_time":1.837943154},
{"learn":[5.161421246],"iteration":119,"passed_time":0.2487240208,"remaining_time":1.823976152},
{"learn":[5.158223542],"iteration":120,"passed_time":0.2492120525,"remaining_time":1.810391687},
{"learn":[5.15470988],"iteration":121,"passed_time":0.2495927284,"remaining_time":1.796249307},
{"learn":[5.146388143],"iteration":122,"passed_time":0.2500822698,"remaining_time":1.783106915},
{"learn":[5.139529364],"iteration":123,"passed_time":0.2505855229,"remaining_time":1.770265468},
{"learn":[5.134276023],"iteration":124,"passed_time":0.2510144804,"remaining_time":1.757101363},
{"learn":[5.128536065],"iteration":125,"passed_time":0.2515209023,"remaining_time":1.744676735},
{"learn":[5.123300353],"iteration":126,"passed_time":0.251869713,"remaining_time":1.731356373},
{"learn":[5.116200518],"iteration":127,"passed_time":0.2523510876,"remaining_time":1.719141784},
{"learn":[5.108728704],"iteration":128,"passed_time":0.2528523132,"remaining_time":1.707243138},
{"learn":[5.104075866],"iteration":129,"passed_time":0.2533032564,"remaining_time":1.695183331},
{"learn":[5.100317606],"iteration":130,"passed_time":0.2537633392,"remaining_time":1.683361388},
{"learn":[5.095814182],"iteration":131,"passed_time":0.2542606982,"remaining_time":1.671956712},
{"learn":[5.092146915],"iteration":132,"passed_time":0.2547789449,"remaining_time":1.66085222},
{"learn":[5.085258329],"iteration":133,"passed_time":0.2554357845,"remaining_time":1.650801413},
{"learn":[5.079219421],"iteration":134,"passed_time":0.2560628381,"remaining_time":1.640698926},
{"learn":[5.076476829],"iteration":135,"passed_time":0.256593039,"remaining_time":1.630120483},
{"learn":[5.072133867],"iteration":136,"passed_time":0.2571192468,"remaining_time":1.619663576},
{"learn":[5.067031564],"iteration":137,"passed_time":0.2576425937,"remaining_time":1.609332723},
{"learn":[5.061358312],"iteration":138,"passed_time":0.2581486617,"remaining_time":1.599035955},
{"learn":[5.056759124],"iteration":139,"passed_time":0.2586551894,"remaining_time":1.588881878},
{"learn":[5.050254],"iteration":140,"passed_time":0.2591243628,"remaining_time":1.578637076},
{"learn":[5.048376474],"iteration":141,"passed_time":0.2594381508,"remaining_time":1.56759108},
{"learn":[5.042603751],"iteration":142,"passed_time":0.2599120258,"remaining_time":1.557654588},
{"learn":[5.037477349],"iteration":143,"passed_time":0.2603793287,"remaining_time":1.547810454},
{"learn":[5.03230489],"iteration":144,"passed_time":0.2608687047,"remaining_time":1.53822581},
{"learn":[5.025976187],"iteration":145,"passed_time":0.2613665906,"remaining_time":1.528815537},
{"learn":[5.01952451],"iteration":146,"passed_time":0.2618445628,"remaining_time":1.519410966},
{"learn":[5.017569424],"iteration":147,"passed_time":0.2623324275,"remaining_time":1.510183974},
{"learn":[5.008962367],"iteration":148,"passed_time":0.2627749665,"remaining_time":1.500815412},
{"learn":[5.003880266],"iteration":149,"passed_time":0.2632935153,"remaining_time":1.491996587},
{"learn":[4.996387564],"iteration":150,"passed_time":0.2637514588,"remaining_time":1.482946944},
{"learn":[4.993361683],"iteration":151,"passed_time":0.2642385943,"remaining_time":1.47417321},
{"learn":[4.99005752],"iteration":152,"passed_time":0.2647312976,"remaining_time":1.465538622},
{"learn":[4.986908764],"iteration":153,"passed_time":0.2652142226,"remaining_time":1.456956054},
{"learn":[4.985207175],"iteration":154,"passed_time":0.2657108922,"remaining_time":1.448552928},
{"learn":[4.979003494],"iteration":155,"passed_time":0.2662285854,"remaining_time":1.440364911},
{"learn":[4.973142217],"iteration":156,"passed_time":0.2667124272,"remaining_time":1.432092842},
{"learn":[4.967056696],"iteration":157,"passed_time":0.2672158887,"remaining_time":1.424023913},
{"learn":[4.961460696],"iteration":158,"passed_time":0.2676767199,"remaining_time":1.415824663},
{"learn":[4.954240363],"iteration":159,"passed_time":0.2681753335,"remaining_time":1.407920501},
{"learn":[4.952320707],"iteration":160,"passed_time":0.2684737461,"remaining_time":1.39906505},
{"learn":[4.948337777],"iteration":161,"passed_time":0.2689518623,"remaining_time":1.391244818},
{"learn":[4.943228639],"iteration":162,"passed_time":0.2694284633,"remaining_time":1.383506895},
{"learn":[4.938545759],"iteration":163,"passed_time":0.2698815965,"remaining_time":1.375737894},
{"learn":[4.935330572],"iteration":164,"passed_time":0.270591381,"remaining_time":1.369356383},
{"learn":[4.932051543],"iteration":165,"passed_time":0.2712008525,"remaining_time":1.362539223},
{"learn":[4.928964153],"iteration":166,"passed_time":0.2716885004,"remaining_time":1.355188748},
{"learn":[4.922860227],"iteration":167,"passed_time":0.2721812359,"remaining_time":1.347945168},
{"learn":[4.917668772],"iteration":168,"passed_time":0.2726884614,"remaining_time":1.34085273},
{"learn":[4.910365386],"iteration":169,"passed_time":0.2731566444,"remaining_time":1.333647146},
{"learn":[4.906457206],"iteration":170,"passed_time":0.2736501291,"remaining_time":1.326643023},
{"learn":[4.901996508],"iteration":171,"passed_time":0.2741125006,"remaining_time":1.319564829},
{"learn":[4.896816173],"iteration":172,"passed_time":0.2745851439,"remaining_time":1.31261222},
{"learn":[4.891123132],"iteration":173,"passed_time":0.2750838908,"remaining_time":1.30585801},
{"learn":[4.887630202],"iteration":174,"passed_time":0.2755635397,"remaining_time":1.299085258},
{"learn":[4.885259712],"iteration":175,"passed_time":0.2760559037,"remaining_time":1.292443549},
{"learn":[4.880659728],"iteration":176,"passed_time":0.2765387245,"remaining_time":1.285826951},
{"learn":[4.877299723],"iteration":177,"passed_time":0.2770264191,"remaining_time":1.279301778},
{"learn":[4.874038772],"iteration":178,"passed_time":0.2775575407,"remaining_time":1.273043245},
{"learn":[4.86943698],"iteration":179,"passed_time":0.2780414001,"remaining_time":1.266633045},
{"learn":[4.861268711],"iteration":180,"passed_time":0.2785226453,"remaining_time":1.2602765},
{"learn":[4.858673056],"iteration":181,"passed_time":0.2789839943,"remaining_time":1.253895095},
{"learn":[4.854036207],"iteration":182,"passed_time":0.2794736261,"remaining_time":1.247704659},
{"learn":[4.85130244],"iteration":183,"passed_time":0.2799637734,"remaining_time":1.241578473},
{"learn":[4.847510084],"iteration":184,"passed_time":0.2804422189,"remaining_time":1.235461667},
{"learn":[4.845691673],"iteration":185,"passed_time":0.2809130591,"remaining_time":1.229372205},
{"learn":[4.842058646],"iteration":186,"passed_time":0.2813688831,"remaining_time":1.223277551},
{"learn":[4.838623675],"iteration":187,"passed_time":0.2818585463,"remaining_time":1.217389041},
{"learn":[4.834602161],"iteration":188,"passed_time":0.2823531662,"remaining_time":1.21157893},
{"learn":[4.830858976],"iteration":189,"passed_time":0.2828349743,"remaining_time":1.205770154},
{"learn":[4.827590511],"iteration":190,"passed_time":0.2833070538,"remaining_time":1.199975951},
{"learn":[4.822246226],"iteration":191,"passed_time":0.2837826484,"remaining_time":1.194251979},
{"learn":[4.816686395],"iteration":192,"passed_time":0.284279632,"remaining_time":1.188671829},
{"learn":[4.814797121],"iteration":193,"passed_time":0.2847743277,"remaining_time":1.183134578},
{"learn":[4.811639392],"iteration":194,"passed_time":0.2853525784,"remaining_time":1.177993978},
{"learn":[4.804813432],"iteration":195,"passed_time":0.2860153992,"remaining_time":1.173246842},
{"learn":[4.80251613],"iteration":196,"passed_time":0.2865539392,"remaining_time":1.168034585},
{"learn":[4.800087884],"iteration":197,"passed_time":0.2870237583,"remaining_time":1.162591183},
{"learn":[4.794773135],"iteration":198,"passed_time":0.2875420621,"remaining_time":1.157392923},
{"learn":[4.791664833],"iteration":199,"passed_time":0.2880454492,"remaining_time":1.152181797},
{"learn":[4.785989873],"iteration":200,"passed_time":0.2885444849,"remaining_time":1.147000216},
{"learn":[4.782387142],"iteration":201,"passed_time":0.2890392533,"remaining_time":1.141848139},
{"learn":[4.778623704],"iteration":202,"passed_time":0.2895483799,"remaining_time":1.136798319},
{"learn":[4.775772178],"iteration":203,"passed_time":0.2900259116,"remaining_time":1.131669734},
{"learn":[4.77023101],"iteration":204,"passed_time":0.2904668329,"remaining_time":1.126444547},
{"learn":[4.764496689],"iteration":205,"passed_time":0.290949682,"remaining_time":1.121427415},
{"learn":[4.763138716],"iteration":206,"passed_time":0.2914379902,"remaining_time":1.116475006},
{"learn":[4.758053283],"iteration":207,"passed_time":0.2919438921,"remaining_time":1.111632512},
{"learn":[4.755063788],"iteration":208,"passed_time":0.2923840649,"remaining_time":1.106582753},
{"learn":[4.752465267],"iteration":209,"passed_time":0.2928861591,"remaining_time":1.101809837},
{"learn":[4.748067377],"iteration":210,"passed_time":0.2933709377,"remaining_time":1.097012653},
{"learn":[4.744163298],"iteration":211,"passed_time":0.2938775857,"remaining_time":1.092337441},
{"learn":[4.736670896],"iteration":212,"passed_time":0.2943681244,"remaining_time":1.087641849},
{"learn":[4.73349255],"iteration":213,"passed_time":0.2948561078,"remaining_time":1.082976172},
{"learn":[4.731864595],"iteration":214,"passed_time":0.2953556804,"remaining_time":1.07839167},
{"learn":[4.728398311],"iteration":215,"passed_time":0.2958558352,"remaining_time":1.073847105},
{"learn":[4.723865975],"iteration":216,"passed_time":0.2963138124,"remaining_time":1.069187627},
{"learn":[4.723483365],"iteration":217,"passed_time":0.2967858337,"remaining_time":1.064617073},
{"learn":[4.72095416],"iteration":218,"passed_time":0.2972886249,"remaining_time":1.060193681},
{"learn":[4.716173382],"iteration":219,"passed_time":0.2977724782,"remaining_time":1.055738786},
{"learn":[4.710563974],"iteration":220,"passed_time":0.2982712825,"remaining_time":1.05137253},
{"learn":[4.707160263],"iteration":221,"passed_time":0.2987649993,"remaining_time":1.047023286},
{"learn":[4.70408351],"iteration":222,"passed_time":0.299264539,"remaining_time":1.042728909},
{"learn":[4.702501831],"iteration":223,"passed_time":0.2997550685,"remaining_time":1.038437202},
{"learn":[4.700269738],"iteration":224,"passed_time":0.3002313555,"remaining_time":1.034130225},
{"learn":[4.695346302],"iteration":225,"passed_time":0.3007028031,"remaining_time":1.029840573},
{"learn":[4.689769299],"iteration":226,"passed_time":0.3015070969,"remaining_time":1.026718},
{"learn":[4.687919514],"iteration":227,"passed_time":0.3020993642,"remaining_time":1.022897847},
{"learn":[4.682982074],"iteration":228,"passed_time":0.3026602913,"remaining_time":1.019000369},
{"learn":[4.679578702],"iteration":229,"passed_time":0.3032335303,"remaining_time":1.015173123},
{"learn":[4.675751423],"iteration":230,"passed_time":0.3038302203,"remaining_time":1.011452119},
{"learn":[4.672710726],"iteration":231,"passed_time":0.304464224,"remaining_time":1.007881569},
{"learn":[4.6690533],"iteration":232,"passed_time":0.3050004346,"remaining_time":1.004014306},
{"learn":[4.667595702],"iteration":233,"passed_time":0.305540052,"remaining_time":1.000186666},
{"learn":[4.664241291],"iteration":234,"passed_time":0.3060150353,"remaining_time":0.9961766043},
{"learn":[4.662246999],"iteration":235,"passed_time":0.3065252994,"remaining_time":0.992310715},
{"learn":[4.658668443],"iteration":236,"passed_time":0.3070294349,"remaining_time":0.9884534128},
{"learn":[4.658017572],"iteration":237,"passed_time":0.3075070999,"remaining_time":0.9845395384},
{"learn":[4.657656705],"iteration":238,"passed_time":0.308009165,"remaining_time":0.9807321112},
{"learn":[4.653242871],"iteration":239,"passed_time":0.3085110271,"remaining_time":0.9769515858},
{"learn":[4.6507302],"iteration":240,"passed_time":0.3089893868,"remaining_time":0.9731242515},
{"learn":[4.647671336],"iteration":241,"passed_time":0.3094776353,"remaining_time":0.9693555684},
{"learn":[4.645506007],"iteration":242,"passed_time":0.3099603749,"remaining_time":0.9655967234},
{"learn":[4.641297906],"iteration":243,"passed_time":0.310428286,"remaining_time":0.9618187877},
{"learn":[4.63798107],"iteration":244,"passed_time":0.3109408135,"remaining_time":0.9582053641},
{"learn":[4.635062318],"iteration":245,"passed_time":0.3113867496,"remaining_time":0.9544130455},
{"learn":[4.631606017],"iteration":246,"passed_time":0.3118751957,"remaining_time":0.9507774184},
{"learn":[4.630215494],"iteration":247,"passed_time":0.3123309783,"remaining_time":0.9470681278},
{"learn":[4.62729814],"iteration":248,"passed_time":0.3128266177,"remaining_time":0.9435051802},
{"learn":[4.624691756],"iteration":249,"passed_time":0.3132670464,"remaining_time":0.9398011392},
{"learn":[4.621840053],"iteration":250,"passed_time":0.3137536128,"remaining_time":0.9362607807},
{"learn":[4.619602091],"iteration":251,"passed_time":0.314251714,"remaining_time":0.932778897},
{"learn":[4.613584029],"iteration":252,"passed_time":0.3147763014,"remaining_time":0.9293988028},
{"learn":[4.6119388],"iteration":253,"passed_time":0.3152761865,"remaining_time":0.9259686422},
{"learn":[4.60870702],"iteration":254,"passed_time":0.3157905784,"remaining_time":0.9226038467},
{"learn":[4.604771557],"iteration":255,"passed_time":0.3163249515,"remaining_time":0.9193193903},
{"learn":[4.604231277],"iteration":256,"passed_time":0.3170002469,"remaining_time":0.9164637488},
{"learn":[4.600750354],"iteration":257,"passed_time":0.317567635,"remaining_time":0.9133146711},
{"learn":[4.596488253],"iteration":258,"passed_time":0.3180821778,"remaining_time":0.9100343387},
{"learn":[4.59470784],"iteration":259,"passed_time":0.3185875235,"remaining_time":0.9067491054},
{"learn":[4.588818005],"iteration":260,"passed_time":0.3190852586,"remaining_time":0.9034636249},
{"learn":[4.585054174],"iteration":261,"passed_time":0.3195817834,"remaining_time":0.9001960158},
{"learn":[4.581471435],"iteration":262,"passed_time":0.3200714458,"remaining_time":0.8969302493},
{"learn":[4.577555199],"iteration":263,"passed_time":0.3205450879,"remaining_time":0.8936408512},
{"learn":[4.57457145],"iteration":264,"passed_time":0.321036038,"remaining_time":0.8904207091},
{"learn":[4.573029224],"iteration":265,"passed_time":0.3215200858,"remaining_time":0.8872020414},
{"learn":[4.571326203],"iteration":266,"passed_time":0.3220309612,"remaining_time":0.8840775076},
{"learn":[4.571019224],"iteration":267,"passed_time":0.3224521149,"remaining_time":0.8807274184},
{"learn":[4.565766631],"iteration":268,"passed_time":0.3229448168,"remaining_time":0.8775935355},
{"learn":[4.563383471],"iteration":269,"passed_time":0.3234132893,"remaining_time":0.8744137081},
{"learn":[4.558165805],"iteration":270,"passed_time":0.3239073102,"remaining_time":0.8713226166},
{"learn":[4.55629209],"iteration":271,"passed_time":0.3243969979,"remaining_time":0.8682390237},
{"learn":[4.549383848],"iteration":272,"passed_time":0.3248741926,"remaining_time":0.8651411648},
{"learn":[4.546227503],"iteration":273,"passed_time":0.3253774855,"remaining_time":0.8621315857},
{"learn":[4.540620977],"iteration":274,"passed_time":0.3258682487,"remaining_time":0.859107201},
{"learn":[4.532898237],"iteration":275,"passed_time":0.326364487,"remaining_time":0.8561155384},
{"learn":[4.529757367],"iteration":276,"passed_time":0.3268536102,"remaining_time":0.8531233219},
{"learn":[4.52579294],"iteration":277,"passed_time":0.3273292507,"remaining_time":0.8501140972},
{"learn":[4.521572155],"iteration":278,"passed_time":0.3278080869,"remaining_time":0.8471312927},
{"learn":[4.518818099],"iteration":279,"passed_time":0.328306866,"remaining_time":0.8442176554},
{"learn":[4.514012334],"iteration":280,"passed_time":0.3289290786,"remaining_time":0.8416370375},
{"learn":[4.508331416],"iteration":281,"passed_time":0.3295991773,"remaining_time":0.8391922315},
{"learn":[4.506038537],"iteration":282,"passed_time":0.3301103015,"remaining_time":0.8363571951},
{"learn":[4.505805643],"iteration":283,"passed_time":0.330601486,"remaining_time":0.8334882534},
{"learn":[4.501550352],"iteration":284,"passed_time":0.3311087367,"remaining_time":0.8306763044},
{"learn":[4.494692643],"iteration":285,"passed_time":0.3316471201,"remaining_time":0.8279581948},
{"learn":[4.489330245],"iteration":286,"passed_time":0.3322256784,"remaining_time":0.8253550825},
{"learn":[4.484826955],"iteration":287,"passed_time":0.3328705677,"remaining_time":0.8229300145},
{"learn":[4.478285428],"iteration":288,"passed_time":0.3333439723,"remaining_time":0.8200953783},
{"learn":[4.475311671],"iteration":289,"passed_time":0.3342887303,"remaining_time":0.8184310295},
{"learn":[4.471581298],"iteration":290,"passed_time":0.3349075367,"remaining_time":0.8159774692},
{"learn":[4.469164956],"iteration":291,"passed_time":0.3354102085,"remaining_time":0.813254889},
{"learn":[4.462068024],"iteration":292,"passed_time":0.3359205292,"remaining_time":0.8105659186},
{"learn":[4.458540976],"iteration":293,"passed_time":0.3364049532,"remaining_time":0.8078295814},
{"learn":[4.455757458],"iteration":294,"passed_time":0.3368861953,"remaining_time":0.8051009073},
{"learn":[4.453027414],"iteration":295,"passed_time":0.3373638442,"remaining_time":0.8023788727},
{"learn":[4.450659338],"iteration":296,"passed_time":0.3378760286,"remaining_time":0.7997536972},
{"learn":[4.444696901],"iteration":297,"passed_time":0.3383547215,"remaining_time":0.797063807},
{"learn":[4.442052813],"iteration":298,"passed_time":0.338851316,"remaining_time":0.7944306773},
{"learn":[4.440036756],"iteration":299,"passed_time":0.3393742746,"remaining_time":0.7918733073},
{"learn":[4.435017051],"iteration":300,"passed_time":0.339835524,"remaining_time":0.7891861504},
{"learn":[4.429962125],"iteration":301,"passed_time":0.3403246334,"remaining_time":0.7865781262},
{"learn":[4.427666256],"iteration":302,"passed_time":0.3407945215,"remaining_time":0.7839398728},
{"learn":[4.425030004],"iteration":303,"passed_time":0.3412997102,"remaining_time":0.7813967049},
{"learn":[4.422588771],"iteration":304,"passed_time":0.3417892555,"remaining_time":0.7788312542},
{"learn":[4.418936667],"iteration":305,"passed_time":0.3422960083,"remaining_time":0.7763183979},
{"learn":[4.416887976],"iteration":306,"passed_time":0.3427887262,"remaining_time":0.7737869292},
{"learn":[4.413773354],"iteration":307,"passed_time":0.3432997521,"remaining_time":0.7713098325},
{"learn":[4.411129391],"iteration":308,"passed_time":0.3438249404,"remaining_time":0.768877132},
{"learn":[4.40850819],"iteration":309,"passed_time":0.3443307672,"remaining_time":0.766413643},
{"learn":[4.404880292],"iteration":310,"passed_time":0.3448290238,"remaining_time":0.7639459724},
{"learn":[4.404593827],"iteration":311,"passed_time":0.3453292736,"remaining_time":0.7614953212},
{"learn":[4.402139942],"iteration":312,"passed_time":0.3458257072,"remaining_time":0.7590487567},
{"learn":[4.400284725],"iteration":313,"passed_time":0.3463155213,"remaining_time":0.7566001517},
{"learn":[4.395805521],"iteration":314,"passed_time":0.3468259371,"remaining_time":0.7542087838},
{"learn":[4.392838833],"iteration":315,"passed_time":0.3474891167,"remaining_time":0.7521599867},
{"learn":[4.389213061],"iteration":316,"passed_time":0.3480280894,"remaining_time":0.7498523189},
{"learn":[4.3861981],"iteration":317,"passed_time":0.3485430635,"remaining_time":0.747504306},
{"learn":[4.385054234],"iteration":318,"passed_time":0.3490222091,"remaining_time":0.7450912991},
{"learn":[4.379364607],"iteration":319,"passed_time":0.3495201127,"remaining_time":0.7427302394},
{"learn":[4.378387619],"iteration":320,"passed_time":0.3500281378,"remaining_time":0.740402198},
{"learn":[4.375816727],"iteration":321,"passed_time":0.3505115537,"remaining_time":0.7380336442},
{"learn":[4.374600202],"iteration":322,"passed_time":0.350993175,"remaining_time":0.7356730014},
{"learn":[4.37098897],"iteration":323,"passed_time":0.351487817,"remaining_time":0.7333511244},
{"learn":[4.367418484],"iteration":324,"passed_time":0.3519824537,"remaining_time":0.7310404808},
{"learn":[4.363584638],"iteration":325,"passed_time":0.352495486,"remaining_time":0.728779011},
{"learn":[4.360770706],"iteration":326,"passed_time":0.352975894,"remaining_time":0.7264610906},
{"learn":[4.358675808],"iteration":327,"passed_time":0.3534574386,"remaining_time":0.7241567035},
{"learn":[4.354228195],"iteration":328,"passed_time":0.3539589836,"remaining_time":0.7219041885},
{"learn":[4.353773425],"iteration":329,"passed_time":0.3544345545,"remaining_time":0.7196095499},
{"learn":[4.351648009],"iteration":330,"passed_time":0.3549070108,"remaining_time":0.717319608},
{"learn":[4.348209927],"iteration":331,"passed_time":0.3553968816,"remaining_time":0.7150756534},
{"learn":[4.345852733],"iteration":332,"passed_time":0.3559058673,"remaining_time":0.712880521},
{"learn":[4.34237339],"iteration":333,"passed_time":0.3564039976,"remaining_time":0.7106738395},
{"learn":[4.340814362],"iteration":334,"passed_time":0.3568470207,"remaining_time":0.7083679664},
{"learn":[4.339707068],"iteration":335,"passed_time":0.3574329105,"remaining_time":0.7063555135},
{"learn":[4.335430786],"iteration":336,"passed_time":0.3579730452,"remaining_time":0.7042615103},
{"learn":[4.33521887],"iteration":337,"passed_time":0.3584568135,"remaining_time":0.7020663033},
{"learn":[4.328507238],"iteration":338,"passed_time":0.3589595404,"remaining_time":0.6999181599},
{"learn":[4.326140732],"iteration":339,"passed_time":0.359461355,"remaining_time":0.6977779244},
{"learn":[4.323785636],"iteration":340,"passed_time":0.3599561441,"remaining_time":0.6956337213},
{"learn":[4.320632534],"iteration":341,"passed_time":0.3604168987,"remaining_time":0.6934336823},
{"learn":[4.31973724],"iteration":342,"passed_time":0.3609129471,"remaining_time":0.6913113884},
{"learn":[4.318000924],"iteration":343,"passed_time":0.3613815115,"remaining_time":0.6891461383},
{"learn":[4.312713628],"iteration":344,"passed_time":0.36190016,"remaining_time":0.687085811},
{"learn":[4.308220789],"iteration":345,"passed_time":0.3625810573,"remaining_time":0.6853410736},
{"learn":[4.305890947],"iteration":346,"passed_time":0.3632527611,"remaining_time":0.6835851671},
{"learn":[4.305137856],"iteration":347,"passed_time":0.3637523812,"remaining_time":0.6815130819},
{"learn":[4.304787172],"iteration":348,"passed_time":0.3642500672,"remaining_time":0.6794464004},
{"learn":[4.30350134],"iteration":349,"passed_time":0.3647326834,"remaining_time":0.6773606978},
{"learn":[4.30293809],"iteration":350,"passed_time":0.3652330772,"remaining_time":0.6753170003},
{"learn":[4.299548459],"iteration":351,"passed_time":0.3657191403,"remaining_time":0.6732556901},
{"learn":[4.294768408],"iteration":352,"passed_time":0.3662068825,"remaining_time":0.6712063823},
{"learn":[4.294581479],"iteration":353,"passed_time":0.366661222,"remaining_time":0.6691049419},
{"learn":[4.292551604],"iteration":354,"passed_time":0.3671550636,"remaining_time":0.6670845522},
{"learn":[4.288628894],"iteration":355,"passed_time":0.3676312028,"remaining_time":0.6650407152},
{"learn":[4.287802767],"iteration":356,"passed_time":0.3681250345,"remaining_time":0.6630375271},
{"learn":[4.284566905],"iteration":357,"passed_time":0.3686335422,"remaining_time":0.6610690896},
{"learn":[4.27890232],"iteration":358,"passed_time":0.3691372686,"remaining_time":0.6591002485},
{"learn":[4.276938023],"iteration":359,"passed_time":0.3696229197,"remaining_time":0.6571074128},
{"learn":[4.273425094],"iteration":360,"passed_time":0.3701308483,"remaining_time":0.6551623603},
{"learn":[4.269726505],"iteration":361,"passed_time":0.3705929464,"remaining_time":0.6531444746},
{"learn":[4.265565857],"iteration":362,"passed_time":0.37104906,"remaining_time":0.651124659},
{"learn":[4.262117173],"iteration":363,"passed_time":0.3715517961,"remaining_time":0.6491948965},
{"learn":[4.259185148],"iteration":364,"passed_time":0.3721026928,"remaining_time":0.6473567395},
{"learn":[4.257668507],"iteration":365,"passed_time":0.3725915295,"remaining_time":0.6454181139},
{"learn":[4.253432436],"iteration":366,"passed_time":0.3730839326,"remaining_time":0.6434935404},
{"learn":[4.250216667],"iteration":367,"passed_time":0.3735674381,"remaining_time":0.6415614699},
{"learn":[4.24514828],"iteration":368,"passed_time":0.3740745288,"remaining_time":0.6396775817},
{"learn":[4.244015772],"iteration":369,"passed_time":0.3745524527,"remaining_time":0.6377514735},
{"learn":[4.240329192],"iteration":370,"passed_time":0.3750162114,"remaining_time":0.6358091563},
{"learn":[4.236718014],"iteration":371,"passed_time":0.375495161,"remaining_time":0.633900433},
{"learn":[4.233495944],"iteration":372,"passed_time":0.3759961353,"remaining_time":0.6320363991},
{"learn":[4.230357491],"iteration":373,"passed_time":0.3764953632,"remaining_time":0.630176731},
{"learn":[4.227381215],"iteration":374,"passed_time":0.3769785586,"remaining_time":0.6282975976},
{"learn":[4.226169067],"iteration":375,"passed_time":0.377453296,"remaining_time":0.626411853},
{"learn":[4.225963861],"iteration":376,"passed_time":0.3779894144,"remaining_time":0.624635027},
{"learn":[4.224346548],"iteration":377,"passed_time":0.3785815473,"remaining_time":0.6229569376},
{"learn":[4.222595381],"iteration":378,"passed_time":0.3790900711,"remaining_time":0.6211475834},
{"learn":[4.219700938],"iteration":379,"passed_time":0.3795606776,"remaining_time":0.6192832108},
{"learn":[4.216356207],"iteration":380,"passed_time":0.3800263796,"remaining_time":0.6174181863},
{"learn":[4.214326494],"iteration":381,"passed_time":0.3805143378,"remaining_time":0.6155964941},
{"learn":[4.212901398],"iteration":382,"passed_time":0.3810330896,"remaining_time":0.6138313741},
{"learn":[4.211331091],"iteration":383,"passed_time":0.3815408681,"remaining_time":0.6120551426},
{"learn":[4.208624791],"iteration":384,"passed_time":0.3820114823,"remaining_time":0.6102261341},
{"learn":[4.204659106],"iteration":385,"passed_time":0.382507088,"remaining_time":0.6084439171},
{"learn":[4.202968852],"iteration":386,"passed_time":0.3829901814,"remaining_time":0.6066485302},
{"learn":[4.197261935],"iteration":387,"passed_time":0.383489525,"remaining_time":0.6048855394},
{"learn":[4.196934403],"iteration":388,"passed_time":0.3839786183,"remaining_time":0.6031129455},
{"learn":[4.192479929],"iteration":389,"passed_time":0.3844581347,"remaining_time":0.6013319543},
{"learn":[4.190243116],"iteration":390,"passed_time":0.3849673456,"remaining_time":0.5996038707},
{"learn":[4.185852431],"iteration":391,"passed_time":0.3854697921,"remaining_time":0.5978715143},
{"learn":[4.180967944],"iteration":392,"passed_time":0.385958795,"remaining_time":0.5961246529},
{"learn":[4.178283162],"iteration":393,"passed_time":0.3864568656,"remaining_time":0.5943981232},
{"learn":[4.176341157],"iteration":394,"passed_time":0.386957712,"remaining_time":0.5926820652},
{"learn":[4.176041504],"iteration":395,"passed_time":0.3874091508,"remaining_time":0.5908967856},
{"learn":[4.175564513],"iteration":396,"passed_time":0.3879148765,"remaining_time":0.5892006815},
{"learn":[4.170830274],"iteration":397,"passed_time":0.3884148268,"remaining_time":0.5875018234},
{"learn":[4.167804808],"iteration":398,"passed_time":0.3889028615,"remaining_time":0.585791027},
{"learn":[4.165860548],"iteration":399,"passed_time":0.3893489493,"remaining_time":0.5840234239},
{"learn":[4.160950571],"iteration":400,"passed_time":0.389797413,"remaining_time":0.5822659611},
{"learn":[4.158544115],"iteration":401,"passed_time":0.3902545576,"remaining_time":0.580527924},
{"learn":[4.154448767],"iteration":402,"passed_time":0.3907120974,"remaining_time":0.5787968292},
{"learn":[4.15197457],"iteration":403,"passed_time":0.3911973984,"remaining_time":0.5771129937},
{"learn":[4.149562679],"iteration":404,"passed_time":0.3916593801,"remaining_time":0.5754008177},
{"learn":[4.149327961],"iteration":405,"passed_time":0.3921293708,"remaining_time":0.5737065179},
{"learn":[4.147444889],"iteration":406,"passed_time":0.3926127798,"remaining_time":0.5720377849},
{"learn":[4.147254809],"iteration":407,"passed_time":0.3931528315,"remaining_time":0.5704570496},
{"learn":[4.144589165],"iteration":408,"passed_time":0.3937816572,"remaining_time":0.5690096807},
{"learn":[4.141691034],"iteration":409,"passed_time":0.3942970449,"remaining_time":0.5674030645},
{"learn":[4.138893468],"iteration":410,"passed_time":0.3947980046,"remaining_time":0.5657810821},
{"learn":[4.136964597],"iteration":411,"passed_time":0.395299136,"remaining_time":0.5641647864},
{"learn":[4.133773523],"iteration":412,"passed_time":0.3957764295,"remaining_time":0.56252001},
{"learn":[4.131363444],"iteration":413,"passed_time":0.3962715717,"remaining_time":0.5609061378},
{"learn":[4.130228592],"iteration":414,"passed_time":0.3967514833,"remaining_time":0.5592761874},
{"learn":[4.12884186],"iteration":415,"passed_time":0.3972109235,"remaining_time":0.5576230273},
{"learn":[4.12413494],"iteration":416,"passed_time":0.3976742464,"remaining_time":0.5559810208},
{"learn":[4.119422508],"iteration":417,"passed_time":0.3981804961,"remaining_time":0.5544044227},
{"learn":[4.117038244],"iteration":418,"passed_time":0.3986605241,"remaining_time":0.552796574},
{"learn":[4.116067631],"iteration":419,"passed_time":0.3991078512,"remaining_time":0.5511489373},
{"learn":[4.110343455],"iteration":420,"passed_time":0.3995834817,"remaining_time":0.5495459286},
{"learn":[4.105604544],"iteration":421,"passed_time":0.4000405804,"remaining_time":0.5479228802},
{"learn":[4.103390131],"iteration":422,"passed_time":0.4005342305,"remaining_time":0.5463552032},
{"learn":[4.096724402],"iteration":423,"passed_time":0.4030269921,"remaining_time":0.5475083667},
{"learn":[4.093431279],"iteration":424,"passed_time":0.4037538357,"remaining_time":0.5462551894},
{"learn":[4.091412744],"iteration":425,"passed_time":0.4042723163,"remaining_time":0.5447237314},
{"learn":[4.091192901],"iteration":426,"passed_time":0.4047808815,"remaining_time":0.5431837121},
{"learn":[4.088994581],"iteration":427,"passed_time":0.4052916948,"remaining_time":0.5416515173},
{"learn":[4.087845355],"iteration":428,"passed_time":0.4057727599,"remaining_time":0.5400844893},
{"learn":[4.083650279],"iteration":429,"passed_time":0.4062817471,"remaining_time":0.5385595252},
{"learn":[4.079840652],"iteration":430,"passed_time":0.4067941061,"remaining_time":0.5370437271},
{"learn":[4.075707828],"iteration":431,"passed_time":0.4072634136,"remaining_time":0.5354759697},
{"learn":[4.071345409],"iteration":432,"passed_time":0.4077690964,"remaining_time":0.5339609183},
{"learn":[4.067460475],"iteration":433,"passed_time":0.4082772923,"remaining_time":0.532453796},
{"learn":[4.064914749],"iteration":434,"passed_time":0.4089274308,"remaining_time":0.5311356286},
{"learn":[4.063823175],"iteration":435,"passed_time":0.4095288423,"remaining_time":0.5297574933},
{"learn":[4.058898471],"iteration":436,"passed_time":0.4100331081,"remaining_time":0.5282577571},
{"learn":[4.054120355],"iteration":437,"passed_time":0.4105319852,"remaining_time":0.5267556522},
{"learn":[4.052715901],"iteration":438,"passed_time":0.4109954123,"remaining_time":0.5252128161},
{"learn":[4.052114167],"iteration":439,"passed_time":0.4114917885,"remaining_time":0.5237168217},
{"learn":[4.051377267],"iteration":440,"passed_time":0.4119304424,"remaining_time":0.5221521935},
{"learn":[4.049275336],"iteration":441,"passed_time":0.4124200987,"remaining_time":0.5206570477},
{"learn":[4.047099198],"iteration":442,"passed_time":0.4129851326,"remaining_time":0.5192612164},
{"learn":[4.044348685],"iteration":443,"passed_time":0.4135068373,"remaining_time":0.5178148683},
{"learn":[4.042822379],"iteration":444,"passed_time":0.4140169168,"remaining_time":0.5163581771},
{"learn":[4.041258611],"iteration":445,"passed_time":0.4144902157,"remaining_time":0.5148600437},
{"learn":[4.040044254],"iteration":446,"passed_time":0.41495666,"remaining_time":0.5133580156},
{"learn":[4.036860137],"iteration":447,"passed_time":0.415464129,"remaining_time":0.5119111589},
{"learn":[4.036372284],"iteration":448,"passed_time":0.4160101495,"remaining_time":0.5105157959},
{"learn":[4.03368231],"iteration":449,"passed_time":0.4165537472,"remaining_time":0.5091212466},
{"learn":[4.032439519],"iteration":450,"passed_time":0.4171975025,"remaining_time":0.5078523922},
{"learn":[4.032008634],"iteration":451,"passed_time":0.4178746818,"remaining_time":0.5066268266},
{"learn":[4.030034932],"iteration":452,"passed_time":0.4184411431,"remaining_time":0.5052699895},
{"learn":[4.028173412],"iteration":453,"passed_time":0.41892795,"remaining_time":0.5038208385},
{"learn":[4.023806097],"iteration":454,"passed_time":0.4194285674,"remaining_time":0.5023924598},
{"learn":[4.020239186],"iteration":455,"passed_time":0.4199785418,"remaining_time":0.5010270323},
{"learn":[4.017384838],"iteration":456,"passed_time":0.4204477573,"remaining_time":0.4995692172},
{"learn":[4.016468229],"iteration":457,"passed_time":0.420933868,"remaining_time":0.4981357128},
{"learn":[4.014530169],"iteration":458,"passed_time":0.4214240812,"remaining_time":0.4967111719},
{"learn":[4.012884822],"iteration":459,"passed_time":0.4219139887,"remaining_time":0.4952903346},
{"learn":[4.008924707],"iteration":460,"passed_time":0.4223901087,"remaining_time":0.4938574157},
{"learn":[4.008286778],"iteration":461,"passed_time":0.422861191,"remaining_time":0.4924227722},
{"learn":[4.006444202],"iteration":462,"passed_time":0.4233556293,"remaining_time":0.4910193799},
{"learn":[4.003284363],"iteration":463,"passed_time":0.4238058686,"remaining_time":0.4895688482},
{"learn":[3.999811484],"iteration":464,"passed_time":0.4243779843,"remaining_time":0.4882628421},
{"learn":[3.997483319],"iteration":465,"passed_time":0.4249718406,"remaining_time":0.4869848989},
{"learn":[3.99708333],"iteration":466,"passed_time":0.42551975,"remaining_time":0.4856574448},
{"learn":[3.995860263],"iteration":467,"passed_time":0.4261550799,"remaining_time":0.4844326977},
{"learn":[3.994131111],"iteration":468,"passed_time":0.4267690407,"remaining_time":0.48318627},
{"learn":[3.993125499],"iteration":469,"passed_time":0.4273186624,"remaining_time":0.4818699811},
{"learn":[3.992954084],"iteration":470,"passed_time":0.4278447561,"remaining_time":0.4805305223},
{"learn":[3.990635743],"iteration":471,"passed_time":0.4283389034,"remaining_time":0.4791587732},
{"learn":[3.986678254],"iteration":472,"passed_time":0.4288432189,"remaining_time":0.4778020642},
{"learn":[3.986393291],"iteration":473,"passed_time":0.4293296696,"remaining_time":0.476429127},
{"learn":[3.986152671],"iteration":474,"passed_time":0.4298229796,"remaining_time":0.4750675038},
{"learn":[3.985596662],"iteration":475,"passed_time":0.4302896146,"remaining_time":0.473680164},
{"learn":[3.983853457],"iteration":476,"passed_time":0.4309083218,"remaining_time":0.472463422},
{"learn":[3.983263928],"iteration":477,"passed_time":0.4314762752,"remaining_time":0.4711937565},
{"learn":[3.980067202],"iteration":478,"passed_time":0.4319749914,"remaining_time":0.469851713},
{"learn":[3.978115407],"iteration":479,"passed_time":0.4324544687,"remaining_time":0.4684923411},
{"learn":[3.972661644],"iteration":480,"passed_time":0.4329457351,"remaining_time":0.4671493483},
{"learn":[3.969938254],"iteration":481,"passed_time":0.4334114402,"remaining_time":0.4657824191},
{"learn":[3.968211434],"iteration":482,"passed_time":0.4339044898,"remaining_time":0.4644484911},
{"learn":[3.966113368],"iteration":483,"passed_time":0.4344034335,"remaining_time":0.4631243217},
{"learn":[3.962246044],"iteration":484,"passed_time":0.4348943874,"remaining_time":0.4617950712},
{"learn":[3.961319703],"iteration":485,"passed_time":0.4353805149,"remaining_time":0.4604641659},
{"learn":[3.96078191],"iteration":486,"passed_time":0.4358583269,"remaining_time":0.4591279707},
{"learn":[3.958913633],"iteration":487,"passed_time":0.4363664731,"remaining_time":0.4578271193},
{"learn":[3.957428286],"iteration":488,"passed_time":0.4368586663,"remaining_time":0.4565128395},
{"learn":[3.952641965],"iteration":489,"passed_time":0.4373470986,"remaining_time":0.4551980006},
{"learn":[3.951486786],"iteration":490,"passed_time":0.437839694,"remaining_time":0.4538908437},
{"learn":[3.94938344],"iteration":491,"passed_time":0.4383459145,"remaining_time":0.4526010662},
{"learn":[3.947297924],"iteration":492,"passed_time":0.4388291971,"remaining_time":0.4512908782},
{"learn":[3.946284886],"iteration":493,"passed_time":0.4393153744,"remaining_time":0.4499870029},
{"learn":[3.943288204],"iteration":494,"passed_time":0.4401591243,"remaining_time":0.4490512278},
{"learn":[3.943076488],"iteration":495,"passed_time":0.4408435531,"remaining_time":0.447953933},
{"learn":[3.942347078],"iteration":496,"passed_time":0.4414308481,"remaining_time":0.4467599932},
{"learn":[3.940251541],"iteration":497,"passed_time":0.4419315475,"remaining_time":0.4454811985},
{"learn":[3.939011019],"iteration":498,"passed_time":0.4424223144,"remaining_time":0.4441955502},
{"learn":[3.938760512],"iteration":499,"passed_time":0.4428900754,"remaining_time":0.4428900754},
{"learn":[3.934522727],"iteration":500,"passed_time":0.4433979864,"remaining_time":0.4416279346},
{"learn":[3.930091193],"iteration":501,"passed_time":0.4438538051,"remaining_time":0.4403171214},
{"learn":[3.927671752],"iteration":502,"passed_time":0.4443099707,"remaining_time":0.4390100506},
{"learn":[3.927280041],"iteration":503,"passed_time":0.4448298999,"remaining_time":0.4377691078},
{"learn":[3.925987561],"iteration":504,"passed_time":0.4453242922,"remaining_time":0.4365059894},
{"learn":[3.921645957],"iteration":505,"passed_time":0.4458452094,"remaining_time":0.4352718053},
{"learn":[3.920333743],"iteration":506,"passed_time":0.4463254167,"remaining_time":0.434000849},
{"learn":[3.918659461],"iteration":507,"passed_time":0.4468102681,"remaining_time":0.4327375037},
{"learn":[3.916124385],"iteration":508,"passed_time":0.4472759846,"remaining_time":0.4314587593},
{"learn":[3.913849268],"iteration":509,"passed_time":0.4477646904,"remaining_time":0.4302052908},
{"learn":[3.912826119],"iteration":510,"passed_time":0.4482136957,"remaining_time":0.4289168243},
{"learn":[3.910034145],"iteration":511,"passed_time":0.4486707821,"remaining_time":0.4276393392},
{"learn":[3.90792379],"iteration":512,"passed_time":0.4492046665,"remaining_time":0.4264379582},
{"learn":[3.907823851],"iteration":513,"passed_time":0.4496836804,"remaining_time":0.4251872931},
{"learn":[3.904527401],"iteration":514,"passed_time":0.4501945388,"remaining_time":0.4239696142},
{"learn":[3.903378283],"iteration":515,"passed_time":0.4506722927,"remaining_time":0.4227236234},
{"learn":[3.902170135],"iteration":516,"passed_time":0.4511611746,"remaining_time":0.4214910007},
{"learn":[3.899435429],"iteration":517,"passed_time":0.451633968,"remaining_time":0.4202462791},
{"learn":[3.897497505],"iteration":518,"passed_time":0.4521267158,"remaining_time":0.4190230256},
{"learn":[3.896426119],"iteration":519,"passed_time":0.4526316671,"remaining_time":0.4178138465},
{"learn":[3.896044669],"iteration":520,"passed_time":0.453087413,"remaining_time":0.4165621321},
{"learn":[3.892795942],"iteration":521,"passed_time":0.4535683993,"remaining_time":0.4153365802},
{"learn":[3.892413888],"iteration":522,"passed_time":0.4540176405,"remaining_time":0.4140849226},
{"learn":[3.891738985],"iteration":523,"passed_time":0.4544966038,"remaining_time":0.4128633271},
{"learn":[3.88822057],"iteration":524,"passed_time":0.4550492515,"remaining_time":0.4117112276},
{"learn":[3.883837053],"iteration":525,"passed_time":0.4556158982,"remaining_time":0.4105740223},
{"learn":[3.881769742],"iteration":526,"passed_time":0.4561169223,"remaining_time":0.409380084},
{"learn":[3.880356898],"iteration":527,"passed_time":0.456663276,"remaining_time":0.4082292922},
{"learn":[3.879250273],"iteration":528,"passed_time":0.4571296145,"remaining_time":0.4070095434},
{"learn":[3.877174493],"iteration":529,"passed_time":0.4576870227,"remaining_time":0.4058733975},
{"learn":[3.875854201],"iteration":530,"passed_time":0.458201466,"remaining_time":0.4047014831},
{"learn":[3.873189396],"iteration":531,"passed_time":0.4587036628,"remaining_time":0.4035212673},
{"learn":[3.871583368],"iteration":532,"passed_time":0.4592878204,"remaining_time":0.4024154073},
{"learn":[3.869622679],"iteration":533,"passed_time":0.4598482331,"remaining_time":0.4012907802},
{"learn":[3.866860164],"iteration":534,"passed_time":0.4603470742,"remaining_time":0.4001147468},
{"learn":[3.864498444],"iteration":535,"passed_time":0.4608710757,"remaining_time":0.3989630207},
{"learn":[3.861416322],"iteration":536,"passed_time":0.4613597423,"remaining_time":0.397783167},
{"learn":[3.860265769],"iteration":537,"passed_time":0.4618103486,"remaining_time":0.3965731989},
{"learn":[3.859328725],"iteration":538,"passed_time":0.462311843,"remaining_time":0.3954095726},
{"learn":[3.858521278],"iteration":539,"passed_time":0.4627995721,"remaining_time":0.3942366726},
{"learn":[3.85599111],"iteration":540,"passed_time":0.4632908845,"remaining_time":0.3930693456},
{"learn":[3.852379816],"iteration":541,"passed_time":0.463827233,"remaining_time":0.3919425696},
{"learn":[3.851327537],"iteration":542,"passed_time":0.4642856897,"remaining_time":0.3907524129},
{"learn":[3.847854898],"iteration":543,"passed_time":0.4647971701,"remaining_time":0.3896093926},
{"learn":[3.847083414],"iteration":544,"passed_time":0.4652763487,"remaining_time":0.3884417223},
{"learn":[3.845397429],"iteration":545,"passed_time":0.4657508748,"remaining_time":0.3872727054},
{"learn":[3.841933528],"iteration":546,"passed_time":0.4662214606,"remaining_time":0.3861029647},
{"learn":[3.840996474],"iteration":547,"passed_time":0.4667144643,"remaining_time":0.3849542661},
{"learn":[3.838355966],"iteration":548,"passed_time":0.4671673669,"remaining_time":0.3837750136},
{"learn":[3.83342799],"iteration":549,"passed_time":0.4676378493,"remaining_time":0.3826127858},
{"learn":[3.828161535],"iteration":550,"passed_time":0.4680836789,"remaining_time":0.3814329797},
{"learn":[3.823502399],"iteration":551,"passed_time":0.4685268169,"remaining_time":0.3802536485},
{"learn":[3.820068862],"iteration":552,"passed_time":0.4690122267,"remaining_time":0.3791111489},
{"learn":[3.817951642],"iteration":553,"passed_time":0.4694953921,"remaining_time":0.3779692146},
{"learn":[3.815785958],"iteration":554,"passed_time":0.4700219216,"remaining_time":0.3768644237},
{"learn":[3.81503012],"iteration":555,"passed_time":0.4707325146,"remaining_time":0.3759086987},
{"learn":[3.813529315],"iteration":556,"passed_time":0.4712541213,"remaining_time":0.3748035471},
{"learn":[3.808881326],"iteration":557,"passed_time":0.4717526866,"remaining_time":0.3736822356},
{"learn":[3.808740434],"iteration":558,"passed_time":0.4722102601,"remaining_time":0.3725308134},
{"learn":[3.80714352],"iteration":559,"passed_time":0.472717481,"remaining_time":0.3714208779},
{"learn":[3.80573346],"iteration":560,"passed_time":0.473253255,"remaining_time":0.3703354349},
{"learn":[3.803370052],"iteration":561,"passed_time":0.4737863919,"remaining_time":0.3692498926},
{"learn":[3.803215211],"iteration":562,"passed_time":0.4742509419,"remaining_time":0.3681130757},
{"learn":[3.801309667],"iteration":563,"passed_time":0.4747618141,"remaining_time":0.367014452},
{"learn":[3.800003847],"iteration":564,"passed_time":0.4751853998,"remaining_time":0.3658507061},
{"learn":[3.798026138],"iteration":565,"passed_time":0.4756729972,"remaining_time":0.3647386587},
{"learn":[3.794745847],"iteration":566,"passed_time":0.4761823061,"remaining_time":0.3636453943},
{"learn":[3.794312041],"iteration":567,"passed_time":0.4766780588,"remaining_time":0.3625438757},
{"learn":[3.792205926],"iteration":568,"passed_time":0.4771848523,"remaining_time":0.3614528494},
{"learn":[3.788991061],"iteration":569,"passed_time":0.477694594,"remaining_time":0.3603660972},
{"learn":[3.787391572],"iteration":570,"passed_time":0.4781909579,"remaining_time":0.3592713151},
{"learn":[3.7826445],"iteration":571,"passed_time":0.4786855372,"remaining_time":0.35817729},
{"learn":[3.781700331],"iteration":572,"passed_time":0.4791667256,"remaining_time":0.3570753784},
{"learn":[3.780045374],"iteration":573,"passed_time":0.4796699473,"remaining_time":0.3559919818},
{"learn":[3.775462644],"iteration":574,"passed_time":0.4801376463,"remaining_time":0.3548843472},
{"learn":[3.773711943],"iteration":575,"passed_time":0.4806217041,"remaining_time":0.3537909766},
{"learn":[3.772415806],"iteration":576,"passed_time":0.4811230959,"remaining_time":0.3527124256},
{"learn":[3.770170875],"iteration":577,"passed_time":0.481600705,"remaining_time":0.3516185078},
{"learn":[3.765166479],"iteration":578,"passed_time":0.4820809046,"remaining_time":0.3505286025},
{"learn":[3.763976102],"iteration":579,"passed_time":0.4825775742,"remaining_time":0.3494527261},
{"learn":[3.760761708],"iteration":580,"passed_time":0.483070518,"remaining_time":0.3483761567},
{"learn":[3.758155662],"iteration":581,"passed_time":0.483560673,"remaining_time":0.3472995899},
{"learn":[3.756844548],"iteration":582,"passed_time":0.4840273103,"remaining_time":0.3462082134},
{"learn":[3.753098923],"iteration":583,"passed_time":0.4845370313,"remaining_time":0.3451496661},
{"learn":[3.751618946],"iteration":584,"passed_time":0.4850252499,"remaining_time":0.3440777414},
{"learn":[3.751398464],"iteration":585,"passed_time":0.4855038601,"remaining_time":0.3430010206},
{"learn":[3.749920103],"iteration":586,"passed_time":0.4862429829,"remaining_time":0.3421096285},
{"learn":[3.748237465],"iteration":587,"passed_time":0.4867491483,"remaining_time":0.3410555256},
{"learn":[3.746021536],"iteration":588,"passed_time":0.4872570095,"remaining_time":0.3400044667},
{"learn":[3.74417648],"iteration":589,"passed_time":0.4877627673,"remaining_time":0.3389537875},
{"learn":[3.738788389],"iteration":590,"passed_time":0.4883444025,"remaining_time":0.337957463},
{"learn":[3.736021611],"iteration":591,"passed_time":0.4889051515,"remaining_time":0.336948145},
{"learn":[3.734546151],"iteration":592,"passed_time":0.4894501334,"remaining_time":0.3359295182},
{"learn":[3.733527479],"iteration":593,"passed_time":0.4899614744,"remaining_time":0.3348894926},
{"learn":[3.733026392],"iteration":594,"passed_time":0.4904540782,"remaining_time":0.3338384902},
{"learn":[3.730314752],"iteration":595,"passed_time":0.4909623645,"remaining_time":0.3327999921},
{"learn":[3.727342596],"iteration":596,"passed_time":0.4914541265,"remaining_time":0.3317521155},
{"learn":[3.725459604],"iteration":597,"passed_time":0.4919440057,"remaining_time":0.3307048333},
{"learn":[3.723158842],"iteration":598,"passed_time":0.4924253765,"remaining_time":0.3296537162},
{"learn":[3.722362756],"iteration":599,"passed_time":0.4929184843,"remaining_time":0.3286123229},
{"learn":[3.721443615],"iteration":600,"passed_time":0.4934090437,"remaining_time":0.3275710623},
{"learn":[3.720743486],"iteration":601,"passed_time":0.4939208819,"remaining_time":0.3265456993},
{"learn":[3.720215334],"iteration":602,"passed_time":0.4944026609,"remaining_time":0.3255022494},
{"learn":[3.719436563],"iteration":603,"passed_time":0.4948407457,"remaining_time":0.3244320121},
{"learn":[3.715046574],"iteration":604,"passed_time":0.4953249384,"remaining_time":0.323393968},
{"learn":[3.71443396],"iteration":605,"passed_time":0.4961944119,"remaining_time":0.322608248},
{"learn":[3.712938941],"iteration":606,"passed_time":0.4966491314,"remaining_time":0.321553721},
{"learn":[3.712814764],"iteration":607,"passed_time":0.4971384852,"remaining_time":0.320523497},
{"learn":[3.71235348],"iteration":608,"passed_time":0.4975803394,"remaining_time":0.3194645529},
{"learn":[3.711223749],"iteration":609,"passed_time":0.4980164503,"remaining_time":0.31840396},
{"learn":[3.710755648],"iteration":610,"passed_time":0.4985160467,"remaining_time":0.31738583},
{"learn":[3.708668039],"iteration":611,"passed_time":0.499006485,"remaining_time":0.3163635886},
{"learn":[3.705623591],"iteration":612,"passed_time":0.49949773,"remaining_time":0.3153435914},
{"learn":[3.704045802],"iteration":613,"passed_time":0.4999980678,"remaining_time":0.3143310329},
{"learn":[3.699915209],"iteration":614,"passed_time":0.5005054855,"remaining_time":0.3133245722},
{"learn":[3.696182221],"iteration":615,"passed_time":0.5011104676,"remaining_time":0.3123805512},
{"learn":[3.694263278],"iteration":616,"passed_time":0.5017087298,"remaining_time":0.3114334579},
{"learn":[3.693810229],"iteration":617,"passed_time":0.5021997917,"remaining_time":0.3104212305},
{"learn":[3.690900932],"iteration":618,"passed_time":0.5027242979,"remaining_time":0.3094312722},
{"learn":[3.688020895],"iteration":619,"passed_time":0.5032213382,"remaining_time":0.3084259815},
{"learn":[3.685491894],"iteration":620,"passed_time":0.5037332315,"remaining_time":0.3074313925},
{"learn":[3.684328128],"iteration":621,"passed_time":0.5042259885,"remaining_time":0.3064267261},
{"learn":[3.680640153],"iteration":622,"passed_time":0.5047591077,"remaining_time":0.3054481278},
{"learn":[3.678932783],"iteration":623,"passed_time":0.505265126,"remaining_time":0.3044546272},
{"learn":[3.674167041],"iteration":624,"passed_time":0.5057338926,"remaining_time":0.3034403356},
{"learn":[3.672200976],"iteration":625,"passed_time":0.5062330884,"remaining_time":0.3024459665},
{"learn":[3.670606604],"iteration":626,"passed_time":0.5067523596,"remaining_time":0.3014651198},
{"learn":[3.665506042],"iteration":627,"passed_time":0.5072380466,"remaining_time":0.3004658493},
{"learn":[3.664214007],"iteration":628,"passed_time":0.5077334186,"remaining_time":0.2994739242},
{"learn":[3.66261643],"iteration":629,"passed_time":0.5082293529,"remaining_time":0.2984839056},
{"learn":[3.662118449],"iteration":630,"passed_time":0.5086789541,"remaining_time":0.2974683583},
{"learn":[3.660871366],"iteration":631,"passed_time":0.5091611414,"remaining_time":0.296473576},
{"learn":[3.656695243],"iteration":632,"passed_time":0.5096702052,"remaining_time":0.2954959958},
{"learn":[3.654497801],"iteration":633,"passed_time":0.5101535093,"remaining_time":0.2945050227},
{"learn":[3.654189134],"iteration":634,"passed_time":0.5106374798,"remaining_time":0.2935160317},
{"learn":[3.653957699],"iteration":635,"passed_time":0.5111158763,"remaining_time":0.2925254386},
{"learn":[3.651920725],"iteration":636,"passed_time":0.5115998905,"remaining_time":0.291539655},
{"learn":[3.65106705],"iteration":637,"passed_time":0.5120576233,"remaining_time":0.2905405323},
{"learn":[3.650612844],"iteration":638,"passed_time":0.5124963799,"remaining_time":0.2895323836},
{"learn":[3.649884732],"iteration":639,"passed_time":0.5129758993,"remaining_time":0.2885489434},
{"learn":[3.646276182],"iteration":640,"passed_time":0.5134771265,"remaining_time":0.2875792331},
{"learn":[3.645808194],"iteration":641,"passed_time":0.5139536333,"remaining_time":0.2865971974},
{"learn":[3.645042989],"iteration":642,"passed_time":0.5144392851,"remaining_time":0.2856218115},
{"learn":[3.639864499],"iteration":643,"passed_time":0.514878931,"remaining_time":0.2846225147},
{"learn":[3.637318478],"iteration":644,"passed_time":0.5153915168,"remaining_time":0.2836650984},
{"learn":[3.636344905],"iteration":645,"passed_time":0.5158547156,"remaining_time":0.2826819958},
{"learn":[3.634754643],"iteration":646,"passed_time":0.5163790732,"remaining_time":0.2817338684},
{"learn":[3.630724975],"iteration":647,"passed_time":0.5170321063,"remaining_time":0.2808569466},
{"learn":[3.629408252],"iteration":648,"passed_time":0.5177826717,"remaining_time":0.2800334634},
{"learn":[3.62790646],"iteration":649,"passed_time":0.5183917605,"remaining_time":0.2791340249},
{"learn":[3.627388973],"iteration":650,"passed_time":0.5190034644,"remaining_time":0.2782368803},
{"learn":[3.625163557],"iteration":651,"passed_time":0.5196195588,"remaining_time":0.2773429547},
{"learn":[3.623701985],"iteration":652,"passed_time":0.5202655454,"remaining_time":0.2764657645},
{"learn":[3.622342639],"iteration":653,"passed_time":0.5208359744,"remaining_time":0.2755493076},
{"learn":[3.621130639],"iteration":654,"passed_time":0.5213646502,"remaining_time":0.274611915},
{"learn":[3.619125665],"iteration":655,"passed_time":0.5219068645,"remaining_time":0.273682868},
{"learn":[3.618878783],"iteration":656,"passed_time":0.522416846,"remaining_time":0.2727381707},
{"learn":[3.616207429],"iteration":657,"passed_time":0.5231005089,"remaining_time":0.2718850669},
{"learn":[3.61206486],"iteration":658,"passed_time":0.5237107072,"remaining_time":0.2709944631},
{"learn":[3.611955873],"iteration":659,"passed_time":0.5242153276,"remaining_time":0.2700503203},
{"learn":[3.610713743],"iteration":660,"passed_time":0.5246745074,"remaining_time":0.2690842027},
{"learn":[3.610044025],"iteration":661,"passed_time":0.5251770903,"remaining_time":0.2681417772},
{"learn":[3.607342669],"iteration":662,"passed_time":0.5256588188,"remaining_time":0.2671900783},
{"learn":[3.602510618],"iteration":663,"passed_time":0.5261213504,"remaining_time":0.2662300809},
{"learn":[3.600492392],"iteration":664,"passed_time":0.5266314054,"remaining_time":0.26529552},
{"learn":[3.597171065],"iteration":665,"passed_time":0.5270701727,"remaining_time":0.264326483},
{"learn":[3.594358798],"iteration":666,"passed_time":0.52754368,"remaining_time":0.26337638},
{"learn":[3.593945251],"iteration":667,"passed_time":0.5280495099,"remaining_time":0.2624437684},
{"learn":[3.593607748],"iteration":668,"passed_time":0.5284922779,"remaining_time":0.2614812316},
{"learn":[3.592238714],"iteration":669,"passed_time":0.5289668185,"remaining_time":0.2605358957},
{"learn":[3.590144654],"iteration":670,"passed_time":0.5294490824,"remaining_time":0.2595957498},
{"learn":[3.587151536],"iteration":671,"passed_time":0.529944282,"remaining_time":0.2586632805},
{"learn":[3.586070865],"iteration":672,"passed_time":0.5304395054,"remaining_time":0.2577321223},
{"learn":[3.585102746],"iteration":673,"passed_time":0.5309494455,"remaining_time":0.2568093757},
{"learn":[3.584362847],"iteration":674,"passed_time":0.5314107478,"remaining_time":0.2558644341},
{"learn":[3.581407561],"iteration":675,"passed_time":0.532025871,"remaining_time":0.2549946482},
{"learn":[3.57919422],"iteration":676,"passed_time":0.5327040939,"remaining_time":0.2541557198},
{"learn":[3.577632204],"iteration":677,"passed_time":0.5334131979,"remaining_time":0.2533319317},
{"learn":[3.573911195],"iteration":678,"passed_time":0.5339588358,"remaining_time":0.2524312022},
{"learn":[3.573408216],"iteration":679,"passed_time":0.5345474547,"remaining_time":0.2515517434},
{"learn":[3.571076482],"iteration":680,"passed_time":0.5351042954,"remaining_time":0.2506582529},
{"learn":[3.568177107],"iteration":681,"passed_time":0.5356127272,"remaining_time":0.2497431778},
{"learn":[3.564824621],"iteration":682,"passed_time":0.5360979869,"remaining_time":0.2488185386},
{"learn":[3.562475026],"iteration":683,"passed_time":0.5366400568,"remaining_time":0.2479214298},
{"learn":[3.561226889],"iteration":684,"passed_time":0.5372281159,"remaining_time":0.2470465058},
{"learn":[3.559383467],"iteration":685,"passed_time":0.5377228138,"remaining_time":0.2461296845},
{"learn":[3.555209766],"iteration":686,"passed_time":0.5382084833,"remaining_time":0.2452099785},
{"learn":[3.55345383],"iteration":687,"passed_time":0.538719596,"remaining_time":0.2443030726},
{"learn":[3.552300968],"iteration":688,"passed_time":0.5392149259,"remaining_time":0.2433901915},
{"learn":[3.551253986],"iteration":689,"passed_time":0.5397028128,"remaining_time":0.2424751768},
{"learn":[3.549807725],"iteration":690,"passed_time":0.5401244247,"remaining_time":0.2415317615},
{"learn":[3.547992926],"iteration":691,"passed_time":0.5406207909,"remaining_time":0.2406231266},
{"learn":[3.545438607],"iteration":692,"passed_time":0.5411221344,"remaining_time":0.2397178864},
{"learn":[3.543313763],"iteration":693,"passed_time":0.5415757502,"remaining_time":0.2387927659},
{"learn":[3.542962896],"iteration":694,"passed_time":0.5421420161,"remaining_time":0.2379184387},
{"learn":[3.539800465],"iteration":695,"passed_time":0.5426438621,"remaining_time":0.2370168593},
{"learn":[3.53953187],"iteration":696,"passed_time":0.543141565,"remaining_time":0.2361146258},
{"learn":[3.536332425],"iteration":697,"passed_time":0.5436515097,"remaining_time":0.235218848},
{"learn":[3.534993327],"iteration":698,"passed_time":0.5441064291,"remaining_time":0.2343004795},
{"learn":[3.531637011],"iteration":699,"passed_time":0.5445787215,"remaining_time":0.2333908807},
{"learn":[3.531040284],"iteration":700,"passed_time":0.5450694954,"remaining_time":0.2324904125},
{"learn":[3.529973872],"iteration":701,"passed_time":0.5455211985,"remaining_time":0.2315745259},
{"learn":[3.527325183],"iteration":702,"passed_time":0.5459920701,"remaining_time":0.2306680581},
{"learn":[3.527200815],"iteration":703,"passed_time":0.5464640929,"remaining_time":0.2297633118},
{"learn":[3.523459911],"iteration":704,"passed_time":0.5471213313,"remaining_time":0.2289372946},
{"learn":[3.522729934],"iteration":705,"passed_time":0.5477220913,"remaining_time":0.2280882363},
{"learn":[3.522260582],"iteration":706,"passed_time":0.5482461812,"remaining_time":0.2272081062},
{"learn":[3.518641591],"iteration":707,"passed_time":0.5487867794,"remaining_time":0.2263357904},
{"learn":[3.516856405],"iteration":708,"passed_time":0.5492748984,"remaining_time":0.2254428708},
{"learn":[3.515083413],"iteration":709,"passed_time":0.5497477477,"remaining_time":0.2245448547},
{"learn":[3.514671214],"iteration":710,"passed_time":0.5502316025,"remaining_time":0.2236525079},
{"learn":[3.512617621],"iteration":711,"passed_time":0.5506873385,"remaining_time":0.2227499347},
{"learn":[3.510747971],"iteration":712,"passed_time":0.5511979878,"remaining_time":0.2218707188},
{"learn":[3.508149266],"iteration":713,"passed_time":0.5516829732,"remaining_time":0.2209822554},
{"learn":[3.504557165],"iteration":714,"passed_time":0.5521830583,"remaining_time":0.2201009393},
{"learn":[3.501367208],"iteration":715,"passed_time":0.5526635482,"remaining_time":0.2192129158},
{"learn":[3.497593362],"iteration":716,"passed_time":0.5531402052,"remaining_time":0.2183245161},
{"learn":[3.496291169],"iteration":717,"passed_time":0.5536310832,"remaining_time":0.2174428488},
{"learn":[3.49330374],"iteration":718,"passed_time":0.5541145436,"remaining_time":0.2165593696},
{"learn":[3.490044385],"iteration":719,"passed_time":0.5546230207,"remaining_time":0.2156867303},
{"learn":[3.488891789],"iteration":720,"passed_time":0.5551083768,"remaining_time":0.2148061541},
{"learn":[3.486869081],"iteration":721,"passed_time":0.5556347393,"remaining_time":0.213942462},
{"learn":[3.486303638],"iteration":722,"passed_time":0.5561057457,"remaining_time":0.2130584946},
{"learn":[3.486035862],"iteration":723,"passed_time":0.5565857508,"remaining_time":0.2121790984},
{"learn":[3.482668951],"iteration":724,"passed_time":0.557092267,"remaining_time":0.2113108599},
{"learn":[3.47820549],"iteration":725,"passed_time":0.5575859155,"remaining_time":0.2104387615},
{"learn":[3.474392283],"iteration":726,"passed_time":0.5580448234,"remaining_time":0.2095546586},
{"learn":[3.472268163],"iteration":727,"passed_time":0.5585437035,"remaining_time":0.2086866585},
{"learn":[3.471209164],"iteration":728,"passed_time":0.5589914419,"remaining_time":0.2078006595},
{"learn":[3.470049971],"iteration":729,"passed_time":0.5594893064,"remaining_time":0.206934401},
{"learn":[3.469078654],"iteration":730,"passed_time":0.5599687546,"remaining_time":0.2060623735},
{"learn":[3.468643292],"iteration":731,"passed_time":0.5604335926,"remaining_time":0.2051860694},
{"learn":[3.468134848],"iteration":732,"passed_time":0.5609081999,"remaining_time":0.2043144466},
{"learn":[3.467820182],"iteration":733,"passed_time":0.5613690426,"remaining_time":0.2034389173},
{"learn":[3.465776156],"iteration":734,"passed_time":0.561946175,"remaining_time":0.202606444},
{"learn":[3.463037608],"iteration":735,"passed_time":0.5626770391,"remaining_time":0.2018298075},
{"learn":[3.45965637],"iteration":736,"passed_time":0.5632680249,"remaining_time":0.2010033793},
{"learn":[3.457275091],"iteration":737,"passed_time":0.5637712719,"remaining_time":0.2001464407},
{"learn":[3.455522955],"iteration":738,"passed_time":0.5642530732,"remaining_time":0.1992828851},
{"learn":[3.451270508],"iteration":739,"passed_time":0.564761983,"remaining_time":0.1984298859},
{"learn":[3.450978947],"iteration":740,"passed_time":0.5652460738,"remaining_time":0.1975691405},
{"learn":[3.450608492],"iteration":741,"passed_time":0.5657384439,"remaining_time":0.1967122891},
{"learn":[3.448122004],"iteration":742,"passed_time":0.5662383405,"remaining_time":0.1958590222},
{"learn":[3.445646714],"iteration":743,"passed_time":0.5667287238,"remaining_time":0.1950034318},
{"learn":[3.44411263],"iteration":744,"passed_time":0.5672421513,"remaining_time":0.1941567095},
{"learn":[3.443264164],"iteration":745,"passed_time":0.5677204099,"remaining_time":0.1932989063},
{"learn":[3.439521363],"iteration":746,"passed_time":0.5682389427,"remaining_time":0.1924557597},
{"learn":[3.436809225],"iteration":747,"passed_time":0.5687111272,"remaining_time":0.1915978664},
{"learn":[3.435509465],"iteration":748,"passed_time":0.5692155844,"remaining_time":0.190751818},
{"learn":[3.434450277],"iteration":749,"passed_time":0.5697194779,"remaining_time":0.1899064926},
{"learn":[3.431786753],"iteration":750,"passed_time":0.570193251,"remaining_time":0.1890520899},
{"learn":[3.430150302],"iteration":751,"passed_time":0.5706805756,"remaining_time":0.1882031686},
{"learn":[3.42696281],"iteration":752,"passed_time":0.571174919,"remaining_time":0.1873575099},
{"learn":[3.426870334],"iteration":753,"passed_time":0.5716224712,"remaining_time":0.1864975171},
{"learn":[3.425200309],"iteration":754,"passed_time":0.5721142799,"remaining_time":0.1856529783},
{"learn":[3.423383783],"iteration":755,"passed_time":0.5726030937,"remaining_time":0.1848084059},
{"learn":[3.422752979],"iteration":756,"passed_time":0.5730888474,"remaining_time":0.1839637912},
{"learn":[3.420845924],"iteration":757,"passed_time":0.5736011283,"remaining_time":0.1831285924},
{"learn":[3.418917862],"iteration":758,"passed_time":0.5740924038,"remaining_time":0.1822875749},
{"learn":[3.417095735],"iteration":759,"passed_time":0.5745805765,"remaining_time":0.1814464978},
{"learn":[3.414391848],"iteration":760,"passed_time":0.5750891225,"remaining_time":0.1806127467},
{"learn":[3.41426711],"iteration":761,"passed_time":0.575580814,"remaining_time":0.1797745849},
{"learn":[3.411976013],"iteration":762,"passed_time":0.5760668028,"remaining_time":0.17893556},
{"learn":[3.408614844],"iteration":763,"passed_time":0.5765197261,"remaining_time":0.1780872452},
{"learn":[3.407906721],"iteration":764,"passed_time":0.5769900646,"remaining_time":0.177245314},
{"learn":[3.407494015],"iteration":765,"passed_time":0.5775647704,"remaining_time":0.1764362353},
{"learn":[3.406287128],"iteration":766,"passed_time":0.5782194592,"remaining_time":0.1756520652},
{"learn":[3.404600442],"iteration":767,"passed_time":0.5787355853,"remaining_time":0.1748263747},
{"learn":[3.404012662],"iteration":768,"passed_time":0.5792385833,"remaining_time":0.1739975458},
{"learn":[3.400398762],"iteration":769,"passed_time":0.5797271297,"remaining_time":0.1731652465},
{"learn":[3.399737714],"iteration":770,"passed_time":0.5802079804,"remaining_time":0.1723315532},
{"learn":[3.399185251],"iteration":771,"passed_time":0.5807364218,"remaining_time":0.1715128292},
{"learn":[3.397245411],"iteration":772,"passed_time":0.5812205233,"remaining_time":0.1706818354},
{"learn":[3.396229831],"iteration":773,"passed_time":0.5817093294,"remaining_time":0.1698531117},
{"learn":[3.394002836],"iteration":774,"passed_time":0.5821955434,"remaining_time":0.1690245126},
{"learn":[3.389617243],"iteration":775,"passed_time":0.5826921777,"remaining_time":0.1681998039},
{"learn":[3.385426488],"iteration":776,"passed_time":0.5831736588,"remaining_time":0.1673715906},
{"learn":[3.385072258],"iteration":777,"passed_time":0.5836607821,"remaining_time":0.1665458787},
{"learn":[3.383842366],"iteration":778,"passed_time":0.5841671627,"remaining_time":0.1657264993},
{"learn":[3.380110746],"iteration":779,"passed_time":0.5846309758,"remaining_time":0.1648959163},
{"learn":[3.378595218],"iteration":780,"passed_time":0.5851444026,"remaining_time":0.1640801846},
{"learn":[3.377371219],"iteration":781,"passed_time":0.58562512,"remaining_time":0.1632561076},
{"learn":[3.375814782],"iteration":782,"passed_time":0.5861037808,"remaining_time":0.1624323377},
{"learn":[3.374195887],"iteration":783,"passed_time":0.5865851699,"remaining_time":0.1616101999},
{"learn":[3.373704309],"iteration":784,"passed_time":0.5870424616,"remaining_time":0.1607823302},
{"learn":[3.372971757],"iteration":785,"passed_time":0.5875186038,"remaining_time":0.1599605359},
{"learn":[3.371565136],"iteration":786,"passed_time":0.5879842062,"remaining_time":0.1591367674},
{"learn":[3.3700309],"iteration":787,"passed_time":0.5884689481,"remaining_time":0.1583190571},
{"learn":[3.368186663],"iteration":788,"passed_time":0.5889547071,"remaining_time":0.1575024629},
{"learn":[3.366710398],"iteration":789,"passed_time":0.5894348569,"remaining_time":0.1566852151},
{"learn":[3.364598042],"iteration":790,"passed_time":0.5899692994,"remaining_time":0.1558831651},
{"learn":[3.36348442],"iteration":791,"passed_time":0.5905071278,"remaining_time":0.15508268},
{"learn":[3.362001759],"iteration":792,"passed_time":0.5910173589,"remaining_time":0.1542756536},
{"learn":[3.361580401],"iteration":793,"passed_time":0.5915284878,"remaining_time":0.1534696077},
{"learn":[3.359543675],"iteration":794,"passed_time":0.5920663441,"remaining_time":0.1526711957},
{"learn":[3.35766119],"iteration":795,"passed_time":0.5925850691,"remaining_time":0.1518685353},
{"learn":[3.354592969],"iteration":796,"passed_time":0.593190916,"remaining_time":0.1510887779},
{"learn":[3.350985986],"iteration":797,"passed_time":0.5943046712,"remaining_time":0.1504380245},
{"learn":[3.349589624],"iteration":798,"passed_time":0.5949100163,"remaining_time":0.1496582144},
{"learn":[3.349110856],"iteration":799,"passed_time":0.5954593838,"remaining_time":0.1488648459},
{"learn":[3.345315441],"iteration":800,"passed_time":0.595977293,"remaining_time":0.1480642713},
{"learn":[3.34397474],"iteration":801,"passed_time":0.5964765531,"remaining_time":0.1472597974},
{"learn":[3.343800902],"iteration":802,"passed_time":0.5969666453,"remaining_time":0.1464538345},
{"learn":[3.342329465],"iteration":803,"passed_time":0.5974631739,"remaining_time":0.1456502265},
{"learn":[3.34220347],"iteration":804,"passed_time":0.5979062054,"remaining_time":0.1448344224},
{"learn":[3.341279219],"iteration":805,"passed_time":0.5983971846,"remaining_time":0.1440310841},
{"learn":[3.337329521],"iteration":806,"passed_time":0.5988881323,"remaining_time":0.1432285124},
{"learn":[3.336708453],"iteration":807,"passed_time":0.5993811413,"remaining_time":0.1424272019},
{"learn":[3.333252703],"iteration":808,"passed_time":0.5998590369,"remaining_time":0.1416230853},
{"learn":[3.332186769],"iteration":809,"passed_time":0.6002997574,"remaining_time":0.1408110542},
{"learn":[3.330594851],"iteration":810,"passed_time":0.6007226683,"remaining_time":0.1399957883},
{"learn":[3.327867442],"iteration":811,"passed_time":0.6012191211,"remaining_time":0.1391985157},
{"learn":[3.327563111],"iteration":812,"passed_time":0.6017170285,"remaining_time":0.1384023178},
{"learn":[3.326308994],"iteration":813,"passed_time":0.6022133511,"remaining_time":0.1376064905},
{"learn":[3.326249879],"iteration":814,"passed_time":0.6026784097,"remaining_time":0.1368043016},
{"learn":[3.322336238],"iteration":815,"passed_time":0.6031350893,"remaining_time":0.1360010496},
{"learn":[3.320491154],"iteration":816,"passed_time":0.6036331438,"remaining_time":0.1352079135},
{"learn":[3.320434271],"iteration":817,"passed_time":0.604101686,"remaining_time":0.1344089326},
{"learn":[3.319609638],"iteration":818,"passed_time":0.6046019465,"remaining_time":0.1336177684},
{"learn":[3.316182682],"iteration":819,"passed_time":0.6050952956,"remaining_time":0.1328257966},
{"learn":[3.313126612],"iteration":820,"passed_time":0.6055536665,"remaining_time":0.1320269261},
{"learn":[3.311222803],"iteration":821,"passed_time":0.6060820657,"remaining_time":0.1312440483},
{"learn":[3.309627335],"iteration":822,"passed_time":0.6065464074,"remaining_time":0.1304480123},
{"learn":[3.307974895],"iteration":823,"passed_time":0.6070357006,"remaining_time":0.1296581108},
{"learn":[3.307321505],"iteration":824,"passed_time":0.6074665417,"remaining_time":0.1288565391},
{"learn":[3.306759087],"iteration":825,"passed_time":0.6079430309,"remaining_time":0.1280654811},
{"learn":[3.30484037],"iteration":826,"passed_time":0.6084689909,"remaining_time":0.1272855326},
{"learn":[3.30201994],"iteration":827,"passed_time":0.6091564527,"remaining_time":0.1265397462},
{"learn":[3.299302297],"iteration":828,"passed_time":0.6096863165,"remaining_time":0.1257615924},
{"learn":[3.298132671],"iteration":829,"passed_time":0.6101783902,"remaining_time":0.1249762968},
{"learn":[3.296976183],"iteration":830,"passed_time":0.6106436012,"remaining_time":0.1241862438},
{"learn":[3.293144745],"iteration":831,"passed_time":0.6111459743,"remaining_time":0.1234044756},
{"learn":[3.290284404],"iteration":832,"passed_time":0.6116611589,"remaining_time":0.1226259466},
{"learn":[3.288285745],"iteration":833,"passed_time":0.6121508911,"remaining_time":0.1218429831},
{"learn":[3.286662667],"iteration":834,"passed_time":0.6126493921,"remaining_time":0.1210624547},
{"learn":[3.285692682],"iteration":835,"passed_time":0.6131473684,"remaining_time":0.1202824981},
{"learn":[3.284565611],"iteration":836,"passed_time":0.6136429273,"remaining_time":0.1195027445},
{"learn":[3.283897383],"iteration":837,"passed_time":0.6141357456,"remaining_time":0.1187231394},
{"learn":[3.280712855],"iteration":838,"passed_time":0.6146468967,"remaining_time":0.1179477358},
{"learn":[3.280468341],"iteration":839,"passed_time":0.6151345653,"remaining_time":0.1171684886},
{"learn":[3.277814895],"iteration":840,"passed_time":0.6156366672,"remaining_time":0.1163926636},
{"learn":[3.276316385],"iteration":841,"passed_time":0.6161308894,"remaining_time":0.1156160101},
{"learn":[3.27557063],"iteration":842,"passed_time":0.616620928,"remaining_time":0.1148392476},
{"learn":[3.27499628],"iteration":843,"passed_time":0.6171054845,"remaining_time":0.1140621512},
{"learn":[3.273569958],"iteration":844,"passed_time":0.6175857591,"remaining_time":0.1132849617},
{"learn":[3.269665595],"iteration":845,"passed_time":0.6180660575,"remaining_time":0.1125084786},
{"learn":[3.267984685],"iteration":846,"passed_time":0.6185383025,"remaining_time":0.11173124},
{"learn":[3.267702508],"iteration":847,"passed_time":0.6190251791,"remaining_time":0.1109573434},
{"learn":[3.266671924],"iteration":848,"passed_time":0.6195354401,"remaining_time":0.110188282},
{"learn":[3.265359825],"iteration":849,"passed_time":0.6200125866,"remaining_time":0.1094139859},
{"learn":[3.2618983],"iteration":850,"passed_time":0.6205006313,"remaining_time":0.1086422962},
{"learn":[3.260456253],"iteration":851,"passed_time":0.6211210167,"remaining_time":0.1078942611},
{"learn":[3.258389147],"iteration":852,"passed_time":0.6216553814,"remaining_time":0.1071317011},
{"learn":[3.258108469],"iteration":853,"passed_time":0.6221263701,"remaining_time":0.1063588408},
{"learn":[3.256424936],"iteration":854,"passed_time":0.6226603848,"remaining_time":0.1055973752},
{"learn":[3.254817983],"iteration":855,"passed_time":0.6231684582,"remaining_time":0.1048320771},
{"learn":[3.253898449],"iteration":856,"passed_time":0.6236577698,"remaining_time":0.1040642486},
{"learn":[3.253023652],"iteration":857,"passed_time":0.6242857242,"remaining_time":0.103320015},
{"learn":[3.252845542],"iteration":858,"passed_time":0.6248930195,"remaining_time":0.1025726609},
{"learn":[3.252316026],"iteration":859,"passed_time":0.6254927156,"remaining_time":0.1018243956},
{"learn":[3.24975301],"iteration":860,"passed_time":0.626001018,"remaining_time":0.1010617207},
{"learn":[3.249151075],"iteration":861,"passed_time":0.6265921976,"remaining_time":0.100312904},
{"learn":[3.246257135],"iteration":862,"passed_time":0.6270758954,"remaining_time":0.09954739012},
{"learn":[3.243826471],"iteration":863,"passed_time":0.6275543892,"remaining_time":0.09878170942},
{"learn":[3.243190653],"iteration":864,"passed_time":0.6280735248,"remaining_time":0.09802303566},
{"learn":[3.24008797],"iteration":865,"passed_time":0.6285662979,"remaining_time":0.09726083593},
{"learn":[3.240036811],"iteration":866,"passed_time":0.6290564873,"remaining_time":0.09649886138},
{"learn":[3.238676314],"iteration":867,"passed_time":0.6295389711,"remaining_time":0.09573634122},
{"learn":[3.237848782],"iteration":868,"passed_time":0.6300312179,"remaining_time":0.09497593734},
{"learn":[3.236405498],"iteration":869,"passed_time":0.6304830627,"remaining_time":0.09421011282},
{"learn":[3.233378068],"iteration":870,"passed_time":0.6309673411,"remaining_time":0.09344981286},
{"learn":[3.233169169],"iteration":871,"passed_time":0.6314667452,"remaining_time":0.09269236627},
{"learn":[3.232434885],"iteration":872,"passed_time":0.6319620498,"remaining_time":0.09193491446},
{"learn":[3.229978115],"iteration":873,"passed_time":0.6324563862,"remaining_time":0.09117792296},
{"learn":[3.229648848],"iteration":874,"passed_time":0.6329492658,"remaining_time":0.09042132368},
{"learn":[3.227208761],"iteration":875,"passed_time":0.6334425206,"remaining_time":0.08966537963},
{"learn":[3.226258869],"iteration":876,"passed_time":0.6339289943,"remaining_time":0.08890908358},
{"learn":[3.225331995],"iteration":877,"passed_time":0.6344191815,"remaining_time":0.08815391815},
{"learn":[3.221968268],"iteration":878,"passed_time":0.6349157729,"remaining_time":0.08740023723},
{"learn":[3.221166317],"iteration":879,"passed_time":0.6354010517,"remaining_time":0.08664559796},
{"learn":[3.220047503],"iteration":880,"passed_time":0.6359589084,"remaining_time":0.08590137355},
{"learn":[3.21982781],"iteration":881,"passed_time":0.6365443597,"remaining_time":0.08516126354},
{"learn":[3.216693405],"iteration":882,"passed_time":0.6370508965,"remaining_time":0.08441104744},
{"learn":[3.214798761],"iteration":883,"passed_time":0.6375518624,"remaining_time":0.08366065163},
{"learn":[3.214395085],"iteration":884,"passed_time":0.6380426938,"remaining_time":0.08290950258},
{"learn":[3.213470696],"iteration":885,"passed_time":0.638569591,"remaining_time":0.08216358168},
{"learn":[3.211595017],"iteration":886,"passed_time":0.6390742152,"remaining_time":0.08141531715},
{"learn":[3.210965255],"iteration":887,"passed_time":0.6396529749,"remaining_time":0.08067695179},
{"learn":[3.209413583],"iteration":888,"passed_time":0.6403021062,"remaining_time":0.07994773204},
{"learn":[3.208331683],"iteration":889,"passed_time":0.6407803349,"remaining_time":0.07919756949},
{"learn":[3.207110711],"iteration":890,"passed_time":0.6413020373,"remaining_time":0.07845333565},
{"learn":[3.204519413],"iteration":891,"passed_time":0.6417797061,"remaining_time":0.07770426935},
{"learn":[3.201421296],"iteration":892,"passed_time":0.6422758403,"remaining_time":0.07695802342},
{"learn":[3.200691259],"iteration":893,"passed_time":0.6427823756,"remaining_time":0.07621357026},
{"learn":[3.200485067],"iteration":894,"passed_time":0.6432767113,"remaining_time":0.07546821752},
{"learn":[3.197467568],"iteration":895,"passed_time":0.6437695984,"remaining_time":0.07472325696},
{"learn":[3.195838544],"iteration":896,"passed_time":0.6442460861,"remaining_time":0.07397697533},
{"learn":[3.195671746],"iteration":897,"passed_time":0.6447123213,"remaining_time":0.07323013004},
{"learn":[3.194213094],"iteration":898,"passed_time":0.6452050407,"remaining_time":0.07248688444},
{"learn":[3.192884691],"iteration":899,"passed_time":0.6457119904,"remaining_time":0.07174577672},
{"learn":[3.188364239],"iteration":900,"passed_time":0.6462086631,"remaining_time":0.07100405954},
{"learn":[3.185219478],"iteration":901,"passed_time":0.6466927829,"remaining_time":0.07026152187},
{"learn":[3.184120387],"iteration":902,"passed_time":0.6471702595,"remaining_time":0.06951884294},
{"learn":[3.183725321],"iteration":903,"passed_time":0.647621562,"remaining_time":0.06877397119},
{"learn":[3.181264554],"iteration":904,"passed_time":0.6481215046,"remaining_time":0.06803485407},
{"learn":[3.180741589],"iteration":905,"passed_time":0.648628786,"remaining_time":0.06729702636},
{"learn":[3.179782639],"iteration":906,"passed_time":0.6490961555,"remaining_time":0.06655561462},
{"learn":[3.176377564],"iteration":907,"passed_time":0.6496186346,"remaining_time":0.06582039029},
{"learn":[3.174078182],"iteration":908,"passed_time":0.6500744425,"remaining_time":0.06507895959},
{"learn":[3.171242379],"iteration":909,"passed_time":0.6518429838,"remaining_time":0.06446798741},
{"learn":[3.170421012],"iteration":910,"passed_time":0.6523238107,"remaining_time":0.06372867086},
{"learn":[3.170087224],"iteration":911,"passed_time":0.6528551751,"remaining_time":0.06299479759},
{"learn":[3.167303059],"iteration":912,"passed_time":0.6533738173,"remaining_time":0.06226015565},
{"learn":[3.16705966],"iteration":913,"passed_time":0.6538874333,"remaining_time":0.06152551342},
{"learn":[3.165667683],"iteration":914,"passed_time":0.6544839456,"remaining_time":0.06079905506},
{"learn":[3.164689733],"iteration":915,"passed_time":0.6551516556,"remaining_time":0.06007940947},
{"learn":[3.163311455],"iteration":916,"passed_time":0.6557637697,"remaining_time":0.05935484502},
{"learn":[3.159425016],"iteration":917,"passed_time":0.6562532636,"remaining_time":0.05861957257},
{"learn":[3.159327058],"iteration":918,"passed_time":0.6567553639,"remaining_time":0.05788594611},
{"learn":[3.15819426],"iteration":919,"passed_time":0.657269343,"remaining_time":0.05715385591},
{"learn":[3.157086603],"iteration":920,"passed_time":0.6577722981,"remaining_time":0.05642129376},
{"learn":[3.153354154],"iteration":921,"passed_time":0.6582896214,"remaining_time":0.0556904452},
{"learn":[3.153261317],"iteration":922,"passed_time":0.6587701136,"remaining_time":0.05495698673},
{"learn":[3.153168454],"iteration":923,"passed_time":0.6592655622,"remaining_time":0.05422530599},
{"learn":[3.152080399],"iteration":924,"passed_time":0.6597610614,"remaining_time":0.05349414011},
{"learn":[3.151635144],"iteration":925,"passed_time":0.6602532079,"remaining_time":0.05276321532},
{"learn":[3.147762655],"iteration":926,"passed_time":0.6607578788,"remaining_time":0.05203379197},
{"learn":[3.147172317],"iteration":927,"passed_time":0.6612645022,"remaining_time":0.05130500448},
{"learn":[3.146254125],"iteration":928,"passed_time":0.6617651082,"remaining_time":0.05057623539},
{"learn":[3.144869828],"iteration":929,"passed_time":0.6622431944,"remaining_time":0.04984626195},
{"learn":[3.143466218],"iteration":930,"passed_time":0.6627504115,"remaining_time":0.04911898861},
{"learn":[3.141919643],"iteration":931,"passed_time":0.6631956773,"remaining_time":0.04838766744},
{"learn":[3.141054135],"iteration":932,"passed_time":0.6636796049,"remaining_time":0.04765973583},
{"learn":[3.139390417],"iteration":933,"passed_time":0.6641655784,"remaining_time":0.04693247128},
{"learn":[3.139025283],"iteration":934,"passed_time":0.6646460025,"remaining_time":0.04620533707},
{"learn":[3.137824183],"iteration":935,"passed_time":0.6651815797,"remaining_time":0.04548250118},
{"learn":[3.135620453],"iteration":936,"passed_time":0.6656994575,"remaining_time":0.04475887495},
{"learn":[3.13443178],"iteration":937,"passed_time":0.6662128836,"remaining_time":0.04403539316},
{"learn":[3.132765713],"iteration":938,"passed_time":0.6667146063,"remaining_time":0.04331159849},
{"learn":[3.131434124],"iteration":939,"passed_time":0.6672053817,"remaining_time":0.04258757755},
{"learn":[3.128384262],"iteration":940,"passed_time":0.6676940162,"remaining_time":0.04186391812},
{"learn":[3.128120455],"iteration":941,"passed_time":0.6681385505,"remaining_time":0.04113804239},
{"learn":[3.126314615],"iteration":942,"passed_time":0.6686503749,"remaining_time":0.04041683072},
{"learn":[3.125409666],"iteration":943,"passed_time":0.6691141597,"remaining_time":0.03969321286},
{"learn":[3.123072589],"iteration":944,"passed_time":0.6696119974,"remaining_time":0.03897212683},
{"learn":[3.122921099],"iteration":945,"passed_time":0.670140119,"remaining_time":0.03825324146},
{"learn":[3.122182662],"iteration":946,"passed_time":0.670734999,"remaining_time":0.03753849519},
{"learn":[3.120040951],"iteration":947,"passed_time":0.6712653415,"remaining_time":0.03682046177},
{"learn":[3.118767799],"iteration":948,"passed_time":0.6717609303,"remaining_time":0.03610095621},
{"learn":[3.118203218],"iteration":949,"passed_time":0.6723511218,"remaining_time":0.03538690115},
{"learn":[3.116343362],"iteration":950,"passed_time":0.6729044865,"remaining_time":0.03467120908},
{"learn":[3.11480829],"iteration":951,"passed_time":0.6734134576,"remaining_time":0.03395361971},
{"learn":[3.112607903],"iteration":952,"passed_time":0.6739148218,"remaining_time":0.033236093},
{"learn":[3.111661241],"iteration":953,"passed_time":0.6743983205,"remaining_time":0.03251815801},
{"learn":[3.110249676],"iteration":954,"passed_time":0.6748655521,"remaining_time":0.03179994748},
{"learn":[3.107333579],"iteration":955,"passed_time":0.675380576,"remaining_time":0.03108446166},
{"learn":[3.107149851],"iteration":956,"passed_time":0.6758154943,"remaining_time":0.03036579546},
{"learn":[3.106867336],"iteration":957,"passed_time":0.6763041709,"remaining_time":0.02965007848},
{"learn":[3.10364681],"iteration":958,"passed_time":0.6768020262,"remaining_time":0.0289352274},
{"learn":[3.102703811],"iteration":959,"passed_time":0.6772838405,"remaining_time":0.02822016002},
{"learn":[3.101469264],"iteration":960,"passed_time":0.6777819731,"remaining_time":0.02750624032},
{"learn":[3.09863569],"iteration":961,"passed_time":0.6782920464,"remaining_time":0.02679324092},
{"learn":[3.09645939],"iteration":962,"passed_time":0.6787734662,"remaining_time":0.02607956205},
{"learn":[3.096240186],"iteration":963,"passed_time":0.6792529489,"remaining_time":0.0253662927},
{"learn":[3.094838828],"iteration":964,"passed_time":0.6797627423,"remaining_time":0.02465460723},
{"learn":[3.094176802],"iteration":965,"passed_time":0.6802218355,"remaining_time":0.02394155529},
{"learn":[3.093182279],"iteration":966,"passed_time":0.6807415593,"remaining_time":0.02323109768},
{"learn":[3.090150687],"iteration":967,"passed_time":0.6812470736,"remaining_time":0.02252056442},
{"learn":[3.088612829],"iteration":968,"passed_time":0.6817462249,"remaining_time":0.02181025075},
{"learn":[3.087153684],"iteration":969,"passed_time":0.6822395855,"remaining_time":0.02110019337},
{"learn":[3.085866843],"iteration":970,"passed_time":0.6827407805,"remaining_time":0.02039081631},
{"learn":[3.082669094],"iteration":971,"passed_time":0.6832370441,"remaining_time":0.01968172555},
{"learn":[3.081047548],"iteration":972,"passed_time":0.6837232734,"remaining_time":0.01897279382},
{"learn":[3.079684322],"iteration":973,"passed_time":0.6842014715,"remaining_time":0.01826410499},
{"learn":[3.07613431],"iteration":974,"passed_time":0.6854006711,"remaining_time":0.01757437618},
{"learn":[3.074005935],"iteration":975,"passed_time":0.6860081709,"remaining_time":0.01686905338},
{"learn":[3.072988853],"iteration":976,"passed_time":0.6865325389,"remaining_time":0.01616197379},
{"learn":[3.072344268],"iteration":977,"passed_time":0.6870523485,"remaining_time":0.0154551653},
{"learn":[3.070654438],"iteration":978,"passed_time":0.6875550088,"remaining_time":0.01474837097},
{"learn":[3.069724506],"iteration":979,"passed_time":0.6880346178,"remaining_time":0.01404152281},
{"learn":[3.067763166],"iteration":980,"passed_time":0.6885373562,"remaining_time":0.0133355859},
{"learn":[3.066737893],"iteration":981,"passed_time":0.6890423534,"remaining_time":0.01263010424},
{"learn":[3.065248174],"iteration":982,"passed_time":0.6895481097,"remaining_time":0.01192504361},
{"learn":[3.063186837],"iteration":983,"passed_time":0.6900402631,"remaining_time":0.01122016688},
{"learn":[3.062880371],"iteration":984,"passed_time":0.6905244964,"remaining_time":0.01051560147},
{"learn":[3.061288645],"iteration":985,"passed_time":0.6909896821,"remaining_time":0.009811212525},
{"learn":[3.059970575],"iteration":986,"passed_time":0.6914816831,"remaining_time":0.009107661479},
{"learn":[3.059576341],"iteration":987,"passed_time":0.6919908993,"remaining_time":0.008404747765},
{"learn":[3.058175919],"iteration":988,"passed_time":0.6924778778,"remaining_time":0.007701978418},
{"learn":[3.056830702],"iteration":989,"passed_time":0.6929724157,"remaining_time":0.00699972137},
{"learn":[3.056336579],"iteration":990,"passed_time":0.6934804239,"remaining_time":0.006298005868},
{"learn":[3.055810414],"iteration":991,"passed_time":0.6939685498,"remaining_time":0.005596520563},
{"learn":[3.055476518],"iteration":992,"passed_time":0.6944888237,"remaining_time":0.004895691607},
{"learn":[3.053331734],"iteration":993,"passed_time":0.6949816251,"remaining_time":0.004195060111},
{"learn":[3.050890374],"iteration":994,"passed_time":0.6954586712,"remaining_time":0.003494767192},
{"learn":[3.04972623],"iteration":995,"passed_time":0.6959578187,"remaining_time":0.00279501132},
{"learn":[3.047217327],"iteration":996,"passed_time":0.6964503949,"remaining_time":0.002095638099},
{"learn":[3.047155483],"iteration":997,"passed_time":0.6968897719,"remaining_time":0.001396572689},
{"learn":[3.04430671],"iteration":998,"passed_time":0.697376768,"remaining_time":0.0006980748428},
{"learn":[3.042664195],"iteration":999,"passed_time":0.6978611092,"remaining_time":0}
]}